{
"meta":{"test_sets":[],"test_metrics":[],"learn_metrics":[{"best_value":"Min","name":"Logloss"}],"launch_mode":"Train","parameters":"","iteration_count":1000,"learn_sets":["learn"],"name":"experiment"},
"iterations":[
{"learn":[0.6445856233],"iteration":0,"passed_time":0.00903818091,"remaining_time":9.029142729},
{"learn":[0.6059853393],"iteration":1,"passed_time":0.01741855839,"remaining_time":8.691860639},
{"learn":[0.5703152356],"iteration":2,"passed_time":0.02582879965,"remaining_time":8.583771082},
{"learn":[0.5419335456],"iteration":3,"passed_time":0.03411679859,"remaining_time":8.495082848},
{"learn":[0.5185200562],"iteration":4,"passed_time":0.04329553718,"remaining_time":8.6158119},
{"learn":[0.4903807771],"iteration":5,"passed_time":0.05217471569,"remaining_time":8.643611233},
{"learn":[0.4676332385],"iteration":6,"passed_time":0.06143143984,"remaining_time":8.714488537},
{"learn":[0.4440944118],"iteration":7,"passed_time":0.07093283495,"remaining_time":8.795671533},
{"learn":[0.4285224288],"iteration":8,"passed_time":0.07948714297,"remaining_time":8.752417632},
{"learn":[0.4123774494],"iteration":9,"passed_time":0.08811130817,"remaining_time":8.723019509},
{"learn":[0.3963729709],"iteration":10,"passed_time":0.09656149474,"remaining_time":8.681756209},
{"learn":[0.3845456691],"iteration":11,"passed_time":0.1046623281,"remaining_time":8.617198345},
{"learn":[0.3712408629],"iteration":12,"passed_time":0.1129606533,"remaining_time":8.576320372},
{"learn":[0.3598036891],"iteration":13,"passed_time":0.1219384903,"remaining_time":8.587953676},
{"learn":[0.3495126],"iteration":14,"passed_time":0.130389423,"remaining_time":8.562238775},
{"learn":[0.3396710326],"iteration":15,"passed_time":0.138536064,"remaining_time":8.519967936},
{"learn":[0.3310267004],"iteration":16,"passed_time":0.1475036894,"remaining_time":8.529183922},
{"learn":[0.3216212707],"iteration":17,"passed_time":0.1557116381,"remaining_time":8.494934923},
{"learn":[0.3136768866],"iteration":18,"passed_time":0.1624596552,"remaining_time":8.388048514},
{"learn":[0.3071198794],"iteration":19,"passed_time":0.1689060582,"remaining_time":8.276396854},
{"learn":[0.3001475829],"iteration":20,"passed_time":0.1754959569,"remaining_time":8.181454373},
{"learn":[0.2942317904],"iteration":21,"passed_time":0.1832268881,"remaining_time":8.145268025},
{"learn":[0.2888559585],"iteration":22,"passed_time":0.1915700316,"remaining_time":8.137561778},
{"learn":[0.2836655479],"iteration":23,"passed_time":0.1983790297,"remaining_time":8.067413874},
{"learn":[0.2766261948],"iteration":24,"passed_time":0.2047271815,"remaining_time":7.984360077},
{"learn":[0.2720201823],"iteration":25,"passed_time":0.2116859576,"remaining_time":7.930081643},
{"learn":[0.267735203],"iteration":26,"passed_time":0.218077857,"remaining_time":7.858879811},
{"learn":[0.2618567575],"iteration":27,"passed_time":0.2243382545,"remaining_time":7.787742264},
{"learn":[0.2574059468],"iteration":28,"passed_time":0.2311957535,"remaining_time":7.741071608},
{"learn":[0.2531249402],"iteration":29,"passed_time":0.2373770274,"remaining_time":7.675190554},
{"learn":[0.2495754453],"iteration":30,"passed_time":0.2442811767,"remaining_time":7.635756781},
{"learn":[0.2460287688],"iteration":31,"passed_time":0.2506874281,"remaining_time":7.583294701},
{"learn":[0.2415967857],"iteration":32,"passed_time":0.2570591331,"remaining_time":7.532611566},
{"learn":[0.2379326421],"iteration":33,"passed_time":0.2633327721,"remaining_time":7.481748759},
{"learn":[0.2341186483],"iteration":34,"passed_time":0.2695442807,"remaining_time":7.431720882},
{"learn":[0.2313233891],"iteration":35,"passed_time":0.2757910826,"remaining_time":7.385072322},
{"learn":[0.2278134745],"iteration":36,"passed_time":0.2821350006,"remaining_time":7.343135285},
{"learn":[0.2247726206],"iteration":37,"passed_time":0.28888088,"remaining_time":7.31324754},
{"learn":[0.2223665348],"iteration":38,"passed_time":0.2955810771,"remaining_time":7.283420899},
{"learn":[0.2204082067],"iteration":39,"passed_time":0.3028168923,"remaining_time":7.267605415},
{"learn":[0.2175207991],"iteration":40,"passed_time":0.3094613969,"remaining_time":7.238377551},
{"learn":[0.213942978],"iteration":41,"passed_time":0.3157647428,"remaining_time":7.20244342},
{"learn":[0.2112823131],"iteration":42,"passed_time":0.3219053144,"remaining_time":7.164264787},
{"learn":[0.2090347278],"iteration":43,"passed_time":0.3283144781,"remaining_time":7.133378206},
{"learn":[0.2067313537],"iteration":44,"passed_time":0.3347142248,"remaining_time":7.103379659},
{"learn":[0.2050449361],"iteration":45,"passed_time":0.3410034681,"remaining_time":7.072115404},
{"learn":[0.2020973426],"iteration":46,"passed_time":0.3472908776,"remaining_time":7.041876732},
{"learn":[0.2003594255],"iteration":47,"passed_time":0.3535076854,"remaining_time":7.01123576},
{"learn":[0.1981879071],"iteration":48,"passed_time":0.3600807758,"remaining_time":6.988506484},
{"learn":[0.1967392277],"iteration":49,"passed_time":0.3664549719,"remaining_time":6.962644466},
{"learn":[0.1947771738],"iteration":50,"passed_time":0.3727054222,"remaining_time":6.935244032},
{"learn":[0.1926964191],"iteration":51,"passed_time":0.3791104786,"remaining_time":6.911475648},
{"learn":[0.1909961632],"iteration":52,"passed_time":0.3853919908,"remaining_time":6.886155006},
{"learn":[0.1890708152],"iteration":53,"passed_time":0.3915921128,"remaining_time":6.86011368},
{"learn":[0.1873806718],"iteration":54,"passed_time":0.3982717813,"remaining_time":6.843033333},
{"learn":[0.1855025746],"iteration":55,"passed_time":0.4047539407,"remaining_time":6.822995001},
{"learn":[0.1827411961],"iteration":56,"passed_time":0.4109789075,"remaining_time":6.799177364},
{"learn":[0.1812921457],"iteration":57,"passed_time":0.4172053079,"remaining_time":6.775989656},
{"learn":[0.1798528284],"iteration":58,"passed_time":0.4231951201,"remaining_time":6.749603526},
{"learn":[0.1786714293],"iteration":59,"passed_time":0.4294830734,"remaining_time":6.72856815},
{"learn":[0.1773064471],"iteration":60,"passed_time":0.435958153,"remaining_time":6.710896814},
{"learn":[0.175769271],"iteration":61,"passed_time":0.442295898,"remaining_time":6.691508908},
{"learn":[0.1742368587],"iteration":62,"passed_time":0.4486538933,"remaining_time":6.672836476},
{"learn":[0.1729321581],"iteration":63,"passed_time":0.4548019433,"remaining_time":6.651478421},
{"learn":[0.1719216055],"iteration":64,"passed_time":0.4612675475,"remaining_time":6.63515626},
{"learn":[0.1701283267],"iteration":65,"passed_time":0.4678268897,"remaining_time":6.620459318},
{"learn":[0.1683270799],"iteration":66,"passed_time":0.4747566996,"remaining_time":6.61116419},
{"learn":[0.1668141876],"iteration":67,"passed_time":0.4813302215,"remaining_time":6.597055389},
{"learn":[0.1656304709],"iteration":68,"passed_time":0.487761944,"remaining_time":6.581251737},
{"learn":[0.1642357718],"iteration":69,"passed_time":0.4941803288,"remaining_time":6.565538654},
{"learn":[0.1631753947],"iteration":70,"passed_time":0.5006795406,"remaining_time":6.551144975},
{"learn":[0.1622620172],"iteration":71,"passed_time":0.5071664615,"remaining_time":6.536812171},
{"learn":[0.1603548721],"iteration":72,"passed_time":0.5136696766,"remaining_time":6.522901235},
{"learn":[0.1592879383],"iteration":73,"passed_time":0.5203290815,"remaining_time":6.511144992},
{"learn":[0.15827818],"iteration":74,"passed_time":0.5266694056,"remaining_time":6.495589335},
{"learn":[0.1575180342],"iteration":75,"passed_time":0.5328274538,"remaining_time":6.478060096},
{"learn":[0.1564227751],"iteration":76,"passed_time":0.5393025744,"remaining_time":6.464626963},
{"learn":[0.155417833],"iteration":77,"passed_time":0.5459807457,"remaining_time":6.453772405},
{"learn":[0.1543978526],"iteration":78,"passed_time":0.5526159522,"remaining_time":6.442522684},
{"learn":[0.153479781],"iteration":79,"passed_time":0.5593873932,"remaining_time":6.432955022},
{"learn":[0.1524998461],"iteration":80,"passed_time":0.5663470665,"remaining_time":6.425592026},
{"learn":[0.1514102927],"iteration":81,"passed_time":0.5731785631,"remaining_time":6.416803914},
{"learn":[0.1504772663],"iteration":82,"passed_time":0.5797373952,"remaining_time":6.405050499},
{"learn":[0.1497180133],"iteration":83,"passed_time":0.5863530069,"remaining_time":6.394039932},
{"learn":[0.1486782618],"iteration":84,"passed_time":0.5930185684,"remaining_time":6.383670472},
{"learn":[0.1481096671],"iteration":85,"passed_time":0.5994154997,"remaining_time":6.370532171},
{"learn":[0.147067616],"iteration":86,"passed_time":0.6059694499,"remaining_time":6.359196641},
{"learn":[0.1461074436],"iteration":87,"passed_time":0.6123559173,"remaining_time":6.346234052},
{"learn":[0.145109925],"iteration":88,"passed_time":0.6187505142,"remaining_time":6.333502454},
{"learn":[0.1444000178],"iteration":89,"passed_time":0.6253903931,"remaining_time":6.323391752},
{"learn":[0.143660444],"iteration":90,"passed_time":0.632073256,"remaining_time":6.3137867},
{"learn":[0.1430394226],"iteration":91,"passed_time":0.6386268036,"remaining_time":6.302968888},
{"learn":[0.1423071171],"iteration":92,"passed_time":0.645105175,"remaining_time":6.29150961},
{"learn":[0.1410413348],"iteration":93,"passed_time":0.6513930591,"remaining_time":6.278320336},
{"learn":[0.1398867024],"iteration":94,"passed_time":0.6575889245,"remaining_time":6.264399755},
{"learn":[0.1391995538],"iteration":95,"passed_time":0.663982615,"remaining_time":6.252502958},
{"learn":[0.1385063509],"iteration":96,"passed_time":0.6703722498,"remaining_time":6.240681872},
{"learn":[0.1378741406],"iteration":97,"passed_time":0.6765013521,"remaining_time":6.226573669},
{"learn":[0.1366365263],"iteration":98,"passed_time":0.6827659267,"remaining_time":6.213859596},
{"learn":[0.1356335114],"iteration":99,"passed_time":0.6891033,"remaining_time":6.2019297},
{"learn":[0.1349811623],"iteration":100,"passed_time":0.6958329708,"remaining_time":6.193602384},
{"learn":[0.1344698762],"iteration":101,"passed_time":0.702004352,"remaining_time":6.180391256},
{"learn":[0.1338580974],"iteration":102,"passed_time":0.7085961451,"remaining_time":6.170978079},
{"learn":[0.1333215196],"iteration":103,"passed_time":0.7151886475,"remaining_time":6.161625271},
{"learn":[0.13265771],"iteration":104,"passed_time":0.721662628,"remaining_time":6.151314782},
{"learn":[0.1315566765],"iteration":105,"passed_time":0.7286390565,"remaining_time":6.145314307},
{"learn":[0.1311488377],"iteration":106,"passed_time":0.7353804862,"remaining_time":6.137334338},
{"learn":[0.1303829192],"iteration":107,"passed_time":0.7425190606,"remaining_time":6.132657427},
{"learn":[0.1295247561],"iteration":108,"passed_time":0.7489310219,"remaining_time":6.121995785},
{"learn":[0.1291283741],"iteration":109,"passed_time":0.7555741427,"remaining_time":6.1132817},
{"learn":[0.1282810294],"iteration":110,"passed_time":0.7622323957,"remaining_time":6.104726124},
{"learn":[0.1277925907],"iteration":111,"passed_time":0.7688385593,"remaining_time":6.095791434},
{"learn":[0.1271299673],"iteration":112,"passed_time":0.7753604453,"remaining_time":6.086236416},
{"learn":[0.1264822958],"iteration":113,"passed_time":0.782122357,"remaining_time":6.078600072},
{"learn":[0.1261255632],"iteration":114,"passed_time":0.7885929784,"remaining_time":6.068737268},
{"learn":[0.1251555436],"iteration":115,"passed_time":0.7947767235,"remaining_time":6.056746755},
{"learn":[0.1246398844],"iteration":116,"passed_time":0.80103861,"remaining_time":6.045445236},
{"learn":[0.1239875605],"iteration":117,"passed_time":0.8072224464,"remaining_time":6.033645743},
{"learn":[0.1235746385],"iteration":118,"passed_time":0.8136886808,"remaining_time":6.024031326},
{"learn":[0.122705693],"iteration":119,"passed_time":0.8200224371,"remaining_time":6.013497872},
{"learn":[0.1222973048],"iteration":120,"passed_time":0.8263248517,"remaining_time":6.002806154},
{"learn":[0.1214824525],"iteration":121,"passed_time":0.8327303934,"remaining_time":5.992928569},
{"learn":[0.1208572014],"iteration":122,"passed_time":0.8394611626,"remaining_time":5.985426338},
{"learn":[0.1201030523],"iteration":123,"passed_time":0.8455233584,"remaining_time":5.973213403},
{"learn":[0.119613728],"iteration":124,"passed_time":0.8520268931,"remaining_time":5.964188252},
{"learn":[0.1191629671],"iteration":125,"passed_time":0.8581209376,"remaining_time":5.952362694},
{"learn":[0.1185417277],"iteration":126,"passed_time":0.8644759608,"remaining_time":5.942421368},
{"learn":[0.1177134861],"iteration":127,"passed_time":0.8707526121,"remaining_time":5.93200217},
{"learn":[0.1170116041],"iteration":128,"passed_time":0.8773484829,"remaining_time":5.923802548},
{"learn":[0.1162222747],"iteration":129,"passed_time":0.8837274758,"remaining_time":5.914176184},
{"learn":[0.1153672763],"iteration":130,"passed_time":0.8899372229,"remaining_time":5.903476692},
{"learn":[0.1150223546],"iteration":131,"passed_time":0.8963698041,"remaining_time":5.89431053},
{"learn":[0.1144050894],"iteration":132,"passed_time":0.9028894312,"remaining_time":5.885752909},
{"learn":[0.1140659872],"iteration":133,"passed_time":0.9091971538,"remaining_time":5.875856233},
{"learn":[0.113770862],"iteration":134,"passed_time":0.9155373482,"remaining_time":5.866220787},
{"learn":[0.113122987],"iteration":135,"passed_time":0.9218657403,"remaining_time":5.85655882},
{"learn":[0.1127968927],"iteration":136,"passed_time":0.9280312367,"remaining_time":5.845919396},
{"learn":[0.1121310653],"iteration":137,"passed_time":0.9347099941,"remaining_time":5.838550833},
{"learn":[0.1118107101],"iteration":138,"passed_time":0.9415445117,"remaining_time":5.832157012},
{"learn":[0.1114554522],"iteration":139,"passed_time":0.9483182458,"remaining_time":5.82538351},
{"learn":[0.1108971891],"iteration":140,"passed_time":0.954772562,"remaining_time":5.816664048},
{"learn":[0.1105406157],"iteration":141,"passed_time":0.9612960652,"remaining_time":5.808394535},
{"learn":[0.1101367431],"iteration":142,"passed_time":0.9674713685,"remaining_time":5.798062677},
{"learn":[0.1096519061],"iteration":143,"passed_time":0.9735784777,"remaining_time":5.787383173},
{"learn":[0.1092967495],"iteration":144,"passed_time":0.9798447515,"remaining_time":5.777705259},
{"learn":[0.1087953467],"iteration":145,"passed_time":0.9864393949,"remaining_time":5.769994817},
{"learn":[0.1081736831],"iteration":146,"passed_time":0.9929860155,"remaining_time":5.762020893},
{"learn":[0.1078044164],"iteration":147,"passed_time":0.9996789532,"remaining_time":5.754908569},
{"learn":[0.1074581466],"iteration":148,"passed_time":1.006198849,"remaining_time":5.74681356},
{"learn":[0.1070149039],"iteration":149,"passed_time":1.012416352,"remaining_time":5.737025994},
{"learn":[0.106748847],"iteration":150,"passed_time":1.018543049,"remaining_time":5.726775157},
{"learn":[0.1063803478],"iteration":151,"passed_time":1.024849943,"remaining_time":5.717583891},
{"learn":[0.1060667368],"iteration":152,"passed_time":1.030965288,"remaining_time":5.707369927},
{"learn":[0.1056267541],"iteration":153,"passed_time":1.037376966,"remaining_time":5.698837101},
{"learn":[0.105106403],"iteration":154,"passed_time":1.043619032,"remaining_time":5.689406981},
{"learn":[0.1047452538],"iteration":155,"passed_time":1.049777804,"remaining_time":5.679567093},
{"learn":[0.104246705],"iteration":156,"passed_time":1.056414981,"remaining_time":5.672342862},
{"learn":[0.1039705058],"iteration":157,"passed_time":1.0629495,"remaining_time":5.664578979},
{"learn":[0.1036902762],"iteration":158,"passed_time":1.069782921,"remaining_time":5.65841155},
{"learn":[0.1032565501],"iteration":159,"passed_time":1.076408852,"remaining_time":5.651146476},
{"learn":[0.1028369869],"iteration":160,"passed_time":1.082775897,"remaining_time":5.642540234},
{"learn":[0.1026084553],"iteration":161,"passed_time":1.088904603,"remaining_time":5.632728746},
{"learn":[0.1021135487],"iteration":162,"passed_time":1.095024099,"remaining_time":5.622915158},
{"learn":[0.1017143614],"iteration":163,"passed_time":1.101236454,"remaining_time":5.613619973},
{"learn":[0.1014584384],"iteration":164,"passed_time":1.107561278,"remaining_time":5.604931317},
{"learn":[0.1009717916],"iteration":165,"passed_time":1.113946619,"remaining_time":5.59657518},
{"learn":[0.1007038924],"iteration":166,"passed_time":1.120201869,"remaining_time":5.587593753},
{"learn":[0.1003834803],"iteration":167,"passed_time":1.126391112,"remaining_time":5.578317888},
{"learn":[0.1000035843],"iteration":168,"passed_time":1.132702807,"remaining_time":5.569680667},
{"learn":[0.09958750643],"iteration":169,"passed_time":1.139238206,"remaining_time":5.562163005},
{"learn":[0.09922375577],"iteration":170,"passed_time":1.1458441,"remaining_time":5.55499859},
{"learn":[0.0988985994],"iteration":171,"passed_time":1.15254644,"remaining_time":5.548304955},
{"learn":[0.09835445984],"iteration":172,"passed_time":1.159402628,"remaining_time":5.542346665},
{"learn":[0.09790434992],"iteration":173,"passed_time":1.166289756,"remaining_time":5.536524935},
{"learn":[0.09767792819],"iteration":174,"passed_time":1.172489862,"remaining_time":5.527452206},
{"learn":[0.0974038198],"iteration":175,"passed_time":1.178786153,"remaining_time":5.518862445},
{"learn":[0.09715454874],"iteration":176,"passed_time":1.185242933,"remaining_time":5.511044822},
{"learn":[0.09678342784],"iteration":177,"passed_time":1.191421698,"remaining_time":5.501958626},
{"learn":[0.09661221043],"iteration":178,"passed_time":1.197695404,"remaining_time":5.49334037},
{"learn":[0.09636879034],"iteration":179,"passed_time":1.20401399,"remaining_time":5.484952623},
{"learn":[0.09600751418],"iteration":180,"passed_time":1.210818634,"remaining_time":5.478787079},
{"learn":[0.09577307583],"iteration":181,"passed_time":1.217357323,"remaining_time":5.471419177},
{"learn":[0.09560228537],"iteration":182,"passed_time":1.223894977,"remaining_time":5.464055718},
{"learn":[0.09517957405],"iteration":183,"passed_time":1.230416626,"remaining_time":5.456630256},
{"learn":[0.09493007033],"iteration":184,"passed_time":1.236980472,"remaining_time":5.449400459},
{"learn":[0.09465631534],"iteration":185,"passed_time":1.243742118,"remaining_time":5.443043462},
{"learn":[0.09429780931],"iteration":186,"passed_time":1.250410576,"remaining_time":5.436276997},
{"learn":[0.09388503521],"iteration":187,"passed_time":1.257075116,"remaining_time":5.429494648},
{"learn":[0.0936031828],"iteration":188,"passed_time":1.263400876,"remaining_time":5.421259842},
{"learn":[0.09342947576],"iteration":189,"passed_time":1.269715564,"remaining_time":5.412997931},
{"learn":[0.09323425716],"iteration":190,"passed_time":1.276218885,"remaining_time":5.40555538},
{"learn":[0.09284608012],"iteration":191,"passed_time":1.283562558,"remaining_time":5.4016591},
{"learn":[0.0926411565],"iteration":192,"passed_time":1.290154735,"remaining_time":5.394584824},
{"learn":[0.09243862177],"iteration":193,"passed_time":1.296282858,"remaining_time":5.385587542},
{"learn":[0.09212099905],"iteration":194,"passed_time":1.302550542,"remaining_time":5.377195825},
{"learn":[0.09188685757],"iteration":195,"passed_time":1.308760461,"remaining_time":5.368588829},
{"learn":[0.09159718795],"iteration":196,"passed_time":1.315005746,"remaining_time":5.360150323},
{"learn":[0.09132336212],"iteration":197,"passed_time":1.32113988,"remaining_time":5.351283758},
{"learn":[0.09114141148],"iteration":198,"passed_time":1.32747164,"remaining_time":5.343240118},
{"learn":[0.09081850717],"iteration":199,"passed_time":1.333899422,"remaining_time":5.335597689},
{"learn":[0.09056801287],"iteration":200,"passed_time":1.340178488,"remaining_time":5.327376179},
{"learn":[0.09028192474],"iteration":201,"passed_time":1.346411276,"remaining_time":5.318991079},
{"learn":[0.09009155246],"iteration":202,"passed_time":1.352811873,"remaining_time":5.311286025},
{"learn":[0.08990672073],"iteration":203,"passed_time":1.359206211,"remaining_time":5.303569333},
{"learn":[0.08967355857],"iteration":204,"passed_time":1.366170204,"remaining_time":5.298074693},
{"learn":[0.08946010903],"iteration":205,"passed_time":1.372924075,"remaining_time":5.291755901},
{"learn":[0.08929481769],"iteration":206,"passed_time":1.379335014,"remaining_time":5.284119158},
{"learn":[0.08913434632],"iteration":207,"passed_time":1.385630002,"remaining_time":5.2760527},
{"learn":[0.08901759461],"iteration":208,"passed_time":1.391804141,"remaining_time":5.267545816},
{"learn":[0.08860106743],"iteration":209,"passed_time":1.397861594,"remaining_time":5.258622188},
{"learn":[0.08847294495],"iteration":210,"passed_time":1.403914849,"remaining_time":5.249710027},
{"learn":[0.08832528147],"iteration":211,"passed_time":1.410575645,"remaining_time":5.243083059},
{"learn":[0.08811154737],"iteration":212,"passed_time":1.417379276,"remaining_time":5.236983522},
{"learn":[0.08794332869],"iteration":213,"passed_time":1.42371462,"remaining_time":5.229157435},
{"learn":[0.08749523863],"iteration":214,"passed_time":1.430164756,"remaining_time":5.22176434},
{"learn":[0.08709543153],"iteration":215,"passed_time":1.43641913,"remaining_time":5.213669435},
{"learn":[0.08689558738],"iteration":216,"passed_time":1.442442498,"remaining_time":5.204757952},
{"learn":[0.08653460397],"iteration":217,"passed_time":1.448661531,"remaining_time":5.19657485},
{"learn":[0.08633066018],"iteration":218,"passed_time":1.454965045,"remaining_time":5.18871096},
{"learn":[0.08611453796],"iteration":219,"passed_time":1.461242623,"remaining_time":5.180769301},
{"learn":[0.08578524724],"iteration":220,"passed_time":1.467725746,"remaining_time":5.173567222},
{"learn":[0.08555394296],"iteration":221,"passed_time":1.474029759,"remaining_time":5.165743929},
{"learn":[0.08533873823],"iteration":222,"passed_time":1.480376335,"remaining_time":5.158082568},
{"learn":[0.08506564255],"iteration":223,"passed_time":1.486620429,"remaining_time":5.150077915},
{"learn":[0.08480103427],"iteration":224,"passed_time":1.492901631,"remaining_time":5.14221673},
{"learn":[0.08461913064],"iteration":225,"passed_time":1.499349072,"remaining_time":5.134938856},
{"learn":[0.0843987094],"iteration":226,"passed_time":1.505724621,"remaining_time":5.127423489},
{"learn":[0.08410028517],"iteration":227,"passed_time":1.512579857,"remaining_time":5.121542322},
{"learn":[0.08388768057],"iteration":228,"passed_time":1.519484717,"remaining_time":5.115819725},
{"learn":[0.08369903871],"iteration":229,"passed_time":1.526957845,"remaining_time":5.111989307},
{"learn":[0.08349588993],"iteration":230,"passed_time":1.533585301,"remaining_time":5.105312105},
{"learn":[0.08331006188],"iteration":231,"passed_time":1.53977929,"remaining_time":5.097200408},
{"learn":[0.08316593412],"iteration":232,"passed_time":1.545927552,"remaining_time":5.088954646},
{"learn":[0.08288317183],"iteration":233,"passed_time":1.55249001,"remaining_time":5.082082683},
{"learn":[0.08264060523],"iteration":234,"passed_time":1.558786347,"remaining_time":5.074347045},
{"learn":[0.0824799335],"iteration":235,"passed_time":1.564830868,"remaining_time":5.065808402},
{"learn":[0.08224390806],"iteration":236,"passed_time":1.571211603,"remaining_time":5.05837322},
{"learn":[0.08195955265],"iteration":237,"passed_time":1.577618412,"remaining_time":5.051030379},
{"learn":[0.08181595703],"iteration":238,"passed_time":1.583675662,"remaining_time":5.042582339},
{"learn":[0.08159541712],"iteration":239,"passed_time":1.58979492,"remaining_time":5.034350579},
{"learn":[0.08140979103],"iteration":240,"passed_time":1.595993701,"remaining_time":5.026386802},
{"learn":[0.0810789351],"iteration":241,"passed_time":1.602645203,"remaining_time":5.019855637},
{"learn":[0.08088922731],"iteration":242,"passed_time":1.609312128,"remaining_time":5.013371528},
{"learn":[0.08065159273],"iteration":243,"passed_time":1.615520447,"remaining_time":5.005464991},
{"learn":[0.08043537251],"iteration":244,"passed_time":1.621813909,"remaining_time":4.9978347},
{"learn":[0.08010954411],"iteration":245,"passed_time":1.628600832,"remaining_time":4.991727754},
{"learn":[0.07993703635],"iteration":246,"passed_time":1.635210582,"remaining_time":4.985075175},
{"learn":[0.07982999178],"iteration":247,"passed_time":1.641340319,"remaining_time":4.976967419},
{"learn":[0.07960917708],"iteration":248,"passed_time":1.647876755,"remaining_time":4.970102181},
{"learn":[0.07927345823],"iteration":249,"passed_time":1.654262627,"remaining_time":4.96278788},
{"learn":[0.07915330117],"iteration":250,"passed_time":1.660506675,"remaining_time":4.955057767},
{"learn":[0.07895364442],"iteration":251,"passed_time":1.666778788,"remaining_time":4.94742275},
{"learn":[0.07880138484],"iteration":252,"passed_time":1.673110401,"remaining_time":4.939974187},
{"learn":[0.07860650226],"iteration":253,"passed_time":1.679376937,"remaining_time":4.932343287},
{"learn":[0.0784536972],"iteration":254,"passed_time":1.685868665,"remaining_time":4.925381002},
{"learn":[0.07820310224],"iteration":255,"passed_time":1.692531693,"remaining_time":4.918920233},
{"learn":[0.07799910829],"iteration":256,"passed_time":1.699505967,"remaining_time":4.913357717},
{"learn":[0.07776756582],"iteration":257,"passed_time":1.705858412,"remaining_time":4.905995898},
{"learn":[0.07746073036],"iteration":258,"passed_time":1.712454742,"remaining_time":4.899339629},
{"learn":[0.07724975008],"iteration":259,"passed_time":1.719296184,"remaining_time":4.893381447},
{"learn":[0.07716177179],"iteration":260,"passed_time":1.725976083,"remaining_time":4.8869591},
{"learn":[0.07704778723],"iteration":261,"passed_time":1.73223459,"remaining_time":4.879347813},
{"learn":[0.07682566111],"iteration":262,"passed_time":1.738498587,"remaining_time":4.8717622},
{"learn":[0.07657591389],"iteration":263,"passed_time":1.74488828,"remaining_time":4.864537022},
{"learn":[0.07643201291],"iteration":264,"passed_time":1.751327447,"remaining_time":4.857455372},
{"learn":[0.07626197168],"iteration":265,"passed_time":1.757577623,"remaining_time":4.84985705},
{"learn":[0.07595154893],"iteration":266,"passed_time":1.763996173,"remaining_time":4.842731066},
{"learn":[0.07583522373],"iteration":267,"passed_time":1.770271299,"remaining_time":4.835218622},
{"learn":[0.07559947382],"iteration":268,"passed_time":1.77660214,"remaining_time":4.827866781},
{"learn":[0.07542002989],"iteration":269,"passed_time":1.782969816,"remaining_time":4.820622096},
{"learn":[0.07526461496],"iteration":270,"passed_time":1.789196106,"remaining_time":4.813003548},
{"learn":[0.07512132666],"iteration":271,"passed_time":1.795461069,"remaining_time":4.805498744},
{"learn":[0.07488140482],"iteration":272,"passed_time":1.80176531,"remaining_time":4.79810762},
{"learn":[0.07467083609],"iteration":273,"passed_time":1.807960321,"remaining_time":4.790435012},
{"learn":[0.07452110075],"iteration":274,"passed_time":1.814454396,"remaining_time":4.78356159},
{"learn":[0.07425210957],"iteration":275,"passed_time":1.820891372,"remaining_time":4.776541134},
{"learn":[0.07409008902],"iteration":276,"passed_time":1.827255053,"remaining_time":4.769333587},
{"learn":[0.07393909199],"iteration":277,"passed_time":1.833536641,"remaining_time":4.761918903},
{"learn":[0.07375471561],"iteration":278,"passed_time":1.839946833,"remaining_time":4.754844684},
{"learn":[0.07361576729],"iteration":279,"passed_time":1.846313528,"remaining_time":4.747663357},
{"learn":[0.07339908127],"iteration":280,"passed_time":1.852924852,"remaining_time":4.741113768},
{"learn":[0.07314390575],"iteration":281,"passed_time":1.859552898,"remaining_time":4.734606315},
{"learn":[0.07302629881],"iteration":282,"passed_time":1.86626601,"remaining_time":4.72831353},
{"learn":[0.07280301566],"iteration":283,"passed_time":1.872938476,"remaining_time":4.721915314},
{"learn":[0.07254989683],"iteration":284,"passed_time":1.879287499,"remaining_time":4.714703725},
{"learn":[0.0724448277],"iteration":285,"passed_time":1.885523178,"remaining_time":4.707215207},
{"learn":[0.07222198942],"iteration":286,"passed_time":1.891567418,"remaining_time":4.699259824},
{"learn":[0.07201132198],"iteration":287,"passed_time":1.89799813,"remaining_time":4.692273154},
{"learn":[0.07188095559],"iteration":288,"passed_time":1.904231668,"remaining_time":4.684805246},
{"learn":[0.07172574233],"iteration":289,"passed_time":1.910531026,"remaining_time":4.677506994},
{"learn":[0.07146043688],"iteration":290,"passed_time":1.917036481,"remaining_time":4.67071775},
{"learn":[0.0712690991],"iteration":291,"passed_time":1.923586297,"remaining_time":4.664038007},
{"learn":[0.07117639856],"iteration":292,"passed_time":1.930575015,"remaining_time":4.658418209},
{"learn":[0.07096214317],"iteration":293,"passed_time":1.937250933,"remaining_time":4.652037955},
{"learn":[0.07085801183],"iteration":294,"passed_time":1.943730911,"remaining_time":4.645187432},
{"learn":[0.07064804345],"iteration":295,"passed_time":1.950359837,"remaining_time":4.638693665},
{"learn":[0.07052856898],"iteration":296,"passed_time":1.956795103,"remaining_time":4.631740598},
{"learn":[0.07038432321],"iteration":297,"passed_time":1.96302724,"remaining_time":4.624312492},
{"learn":[0.07013882799],"iteration":298,"passed_time":1.96962731,"remaining_time":4.617754999},
{"learn":[0.06999336426],"iteration":299,"passed_time":1.975806259,"remaining_time":4.610214605},
{"learn":[0.06988735224],"iteration":300,"passed_time":1.982110949,"remaining_time":4.602975261},
{"learn":[0.06972169087],"iteration":301,"passed_time":1.988475989,"remaining_time":4.595881591},
{"learn":[0.06956891111],"iteration":302,"passed_time":1.994657729,"remaining_time":4.58837108},
{"learn":[0.06942887261],"iteration":303,"passed_time":2.00089767,"remaining_time":4.581002561},
{"learn":[0.06921860161],"iteration":304,"passed_time":2.007371683,"remaining_time":4.574174819},
{"learn":[0.06893680243],"iteration":305,"passed_time":2.013878734,"remaining_time":4.567424318},
{"learn":[0.06880237229],"iteration":306,"passed_time":2.020104385,"remaining_time":4.560040193},
{"learn":[0.06864877039],"iteration":307,"passed_time":2.026562226,"remaining_time":4.553185262},
{"learn":[0.06851313138],"iteration":308,"passed_time":2.033028869,"remaining_time":4.546352584},
{"learn":[0.06837117998],"iteration":309,"passed_time":2.039322066,"remaining_time":4.53913621},
{"learn":[0.06817249623],"iteration":310,"passed_time":2.045673905,"remaining_time":4.532055693},
{"learn":[0.06793984052],"iteration":311,"passed_time":2.051916636,"remaining_time":4.524739249},
{"learn":[0.06783788307],"iteration":312,"passed_time":2.058136831,"remaining_time":4.517380201},
{"learn":[0.06758795615],"iteration":313,"passed_time":2.064339018,"remaining_time":4.509989064},
{"learn":[0.06743920988],"iteration":314,"passed_time":2.07092623,"remaining_time":4.503442754},
{"learn":[0.06723977192],"iteration":315,"passed_time":2.077208121,"remaining_time":4.496235301},
{"learn":[0.06710662718],"iteration":316,"passed_time":2.08352138,"remaining_time":4.48910127},
{"learn":[0.06699665832],"iteration":317,"passed_time":2.090840342,"remaining_time":4.484129286},
{"learn":[0.06680694718],"iteration":318,"passed_time":2.098709296,"remaining_time":4.480316711},
{"learn":[0.06667163359],"iteration":319,"passed_time":2.106834449,"remaining_time":4.477023204},
{"learn":[0.06639618989],"iteration":320,"passed_time":2.114834004,"remaining_time":4.47343392},
{"learn":[0.06623600735],"iteration":321,"passed_time":2.12196,"remaining_time":4.467977889},
{"learn":[0.06611453278],"iteration":322,"passed_time":2.128668682,"remaining_time":4.461636834},
{"learn":[0.06595745113],"iteration":323,"passed_time":2.135451695,"remaining_time":4.455448598},
{"learn":[0.06579606431],"iteration":324,"passed_time":2.142042299,"remaining_time":4.448857083},
{"learn":[0.06567112849],"iteration":325,"passed_time":2.148363706,"remaining_time":4.441709011},
{"learn":[0.06555443784],"iteration":326,"passed_time":2.154690283,"remaining_time":4.434576638},
{"learn":[0.06546582675],"iteration":327,"passed_time":2.160819969,"remaining_time":4.427045791},
{"learn":[0.06528616805],"iteration":328,"passed_time":2.167204047,"remaining_time":4.420042297},
{"learn":[0.06511266829],"iteration":329,"passed_time":2.173497029,"remaining_time":4.412857603},
{"learn":[0.06494284099],"iteration":330,"passed_time":2.179443142,"remaining_time":4.404977227},
{"learn":[0.06484457128],"iteration":331,"passed_time":2.185730611,"remaining_time":4.397795327},
{"learn":[0.06469053391],"iteration":332,"passed_time":2.192210719,"remaining_time":4.391004654},
{"learn":[0.06450351719],"iteration":333,"passed_time":2.199099627,"remaining_time":4.385030993},
{"learn":[0.0643425444],"iteration":334,"passed_time":2.20580674,"remaining_time":4.378690991},
{"learn":[0.06417685612],"iteration":335,"passed_time":2.212240371,"remaining_time":4.371808353},
{"learn":[0.06403139241],"iteration":336,"passed_time":2.218729165,"remaining_time":4.365036903},
{"learn":[0.06395421537],"iteration":337,"passed_time":2.225077781,"remaining_time":4.357992576},
{"learn":[0.06375816716],"iteration":338,"passed_time":2.231400064,"remaining_time":4.35090101},
{"learn":[0.06367636239],"iteration":339,"passed_time":2.237785785,"remaining_time":4.343937112},
{"learn":[0.06350489112],"iteration":340,"passed_time":2.2439102,"remaining_time":4.336471617},
{"learn":[0.06342950719],"iteration":341,"passed_time":2.249975054,"remaining_time":4.328899373},
{"learn":[0.06330058749],"iteration":342,"passed_time":2.25614889,"remaining_time":4.321544667},
{"learn":[0.06315768587],"iteration":343,"passed_time":2.263035799,"remaining_time":4.315556641},
{"learn":[0.0630440245],"iteration":344,"passed_time":2.269681801,"remaining_time":4.309106027},
{"learn":[0.06290071273],"iteration":345,"passed_time":2.276178928,"remaining_time":4.302372887},
{"learn":[0.06275982587],"iteration":346,"passed_time":2.282571428,"remaining_time":4.295444214},
{"learn":[0.06254163714],"iteration":347,"passed_time":2.289436574,"remaining_time":4.289404155},
{"learn":[0.06238420352],"iteration":348,"passed_time":2.296054149,"remaining_time":4.282897567},
{"learn":[0.06217005723],"iteration":349,"passed_time":2.302743904,"remaining_time":4.276524393},
{"learn":[0.06196010729],"iteration":350,"passed_time":2.309835176,"remaining_time":4.270891822},
{"learn":[0.06179297069],"iteration":351,"passed_time":2.316246362,"remaining_time":4.263998985},
{"learn":[0.06166011295],"iteration":352,"passed_time":2.322828488,"remaining_time":4.257422187},
{"learn":[0.06151094124],"iteration":353,"passed_time":2.329343867,"remaining_time":4.250723554},
{"learn":[0.06137633636],"iteration":354,"passed_time":2.335603479,"remaining_time":4.243561251},
{"learn":[0.06127658431],"iteration":355,"passed_time":2.342005947,"remaining_time":4.236662443},
{"learn":[0.06110852008],"iteration":356,"passed_time":2.348278976,"remaining_time":4.229533283},
{"learn":[0.0609958748],"iteration":357,"passed_time":2.35482978,"remaining_time":4.222907035},
{"learn":[0.06085680906],"iteration":358,"passed_time":2.361279808,"remaining_time":4.216101273},
{"learn":[0.0607085197],"iteration":359,"passed_time":2.367745574,"remaining_time":4.209325465},
{"learn":[0.06062839562],"iteration":360,"passed_time":2.373949661,"remaining_time":4.202088181},
{"learn":[0.06057654223],"iteration":361,"passed_time":2.380056392,"remaining_time":4.194685022},
{"learn":[0.06047187705],"iteration":362,"passed_time":2.386303949,"remaining_time":4.187536131},
{"learn":[0.06033049558],"iteration":363,"passed_time":2.392599003,"remaining_time":4.18047518},
{"learn":[0.06022251755],"iteration":364,"passed_time":2.3988881,"remaining_time":4.173408064},
{"learn":[0.06015148626],"iteration":365,"passed_time":2.405245681,"remaining_time":4.16646383},
{"learn":[0.06004493737],"iteration":366,"passed_time":2.411760666,"remaining_time":4.159794281},
{"learn":[0.05987411882],"iteration":367,"passed_time":2.418476502,"remaining_time":4.153470514},
{"learn":[0.05969528819],"iteration":368,"passed_time":2.425323538,"remaining_time":4.147368977},
{"learn":[0.05958637931],"iteration":369,"passed_time":2.432118323,"remaining_time":4.141174442},
{"learn":[0.05944654382],"iteration":370,"passed_time":2.43875847,"remaining_time":4.134714495},
{"learn":[0.05930721785],"iteration":371,"passed_time":2.445499009,"remaining_time":4.128423059},
{"learn":[0.05917208556],"iteration":372,"passed_time":2.452324937,"remaining_time":4.12227275},
{"learn":[0.05910023096],"iteration":373,"passed_time":2.458756836,"remaining_time":4.115459304},
{"learn":[0.05893138758],"iteration":374,"passed_time":2.464934208,"remaining_time":4.108223679},
{"learn":[0.05871053108],"iteration":375,"passed_time":2.471348482,"remaining_time":4.101386842},
{"learn":[0.05865083287],"iteration":376,"passed_time":2.477787288,"remaining_time":4.094592786},
{"learn":[0.05848734429],"iteration":377,"passed_time":2.48449155,"remaining_time":4.088237418},
{"learn":[0.05836049011],"iteration":378,"passed_time":2.49134296,"remaining_time":4.082121315},
{"learn":[0.05824050763],"iteration":379,"passed_time":2.498317544,"remaining_time":4.076202309},
{"learn":[0.0581190961],"iteration":380,"passed_time":2.505046559,"remaining_time":4.069878793},
{"learn":[0.05798804663],"iteration":381,"passed_time":2.511724019,"remaining_time":4.063469748},
{"learn":[0.05784454195],"iteration":382,"passed_time":2.518145091,"remaining_time":4.056646269},
{"learn":[0.05768064219],"iteration":383,"passed_time":2.524911753,"remaining_time":4.050379271},
{"learn":[0.05753378257],"iteration":384,"passed_time":2.531569667,"remaining_time":4.043935961},
{"learn":[0.0573652164],"iteration":385,"passed_time":2.53898834,"remaining_time":4.038701659},
{"learn":[0.05725094482],"iteration":386,"passed_time":2.545634967,"remaining_time":4.032233165},
{"learn":[0.05707424221],"iteration":387,"passed_time":2.55221426,"remaining_time":4.025657544},
{"learn":[0.05693275271],"iteration":388,"passed_time":2.558765892,"remaining_time":4.019038458},
{"learn":[0.05684584248],"iteration":389,"passed_time":2.565137305,"remaining_time":4.012137835},
{"learn":[0.05676131382],"iteration":390,"passed_time":2.571338721,"remaining_time":4.004975144},
{"learn":[0.05666993665],"iteration":391,"passed_time":2.577842981,"remaining_time":3.998287072},
{"learn":[0.05651915478],"iteration":392,"passed_time":2.584555139,"remaining_time":3.991921042},
{"learn":[0.05638290349],"iteration":393,"passed_time":2.591210136,"remaining_time":3.985465337},
{"learn":[0.05627594651],"iteration":394,"passed_time":2.597748673,"remaining_time":3.978830246},
{"learn":[0.05619952416],"iteration":395,"passed_time":2.605115233,"remaining_time":3.973458588},
{"learn":[0.05611120927],"iteration":396,"passed_time":2.612458705,"remaining_time":3.968041812},
{"learn":[0.05599971301],"iteration":397,"passed_time":2.618877908,"remaining_time":3.961217339},
{"learn":[0.05593995904],"iteration":398,"passed_time":2.625274519,"remaining_time":3.954360867},
{"learn":[0.0558615426],"iteration":399,"passed_time":2.632093799,"remaining_time":3.948140699},
{"learn":[0.05573950757],"iteration":400,"passed_time":2.638534299,"remaining_time":3.941351734},
{"learn":[0.0555593514],"iteration":401,"passed_time":2.645065544,"remaining_time":3.934699491},
{"learn":[0.05539946053],"iteration":402,"passed_time":2.651603094,"remaining_time":3.928057189},
{"learn":[0.05533241107],"iteration":403,"passed_time":2.657672143,"remaining_time":3.920724251},
{"learn":[0.05522763823],"iteration":404,"passed_time":2.664093957,"remaining_time":3.913915813},
{"learn":[0.05509369346],"iteration":405,"passed_time":2.670653485,"remaining_time":3.907310764},
{"learn":[0.05488082558],"iteration":406,"passed_time":2.677636742,"remaining_time":3.901323312},
{"learn":[0.05475191805],"iteration":407,"passed_time":2.684114144,"remaining_time":3.894596993},
{"learn":[0.0546676298],"iteration":408,"passed_time":2.690379052,"remaining_time":3.887564841},
{"learn":[0.05454774956],"iteration":409,"passed_time":2.696781211,"remaining_time":3.880733938},
{"learn":[0.05448280252],"iteration":410,"passed_time":2.702817539,"remaining_time":3.873380852},
{"learn":[0.05438787869],"iteration":411,"passed_time":2.708763071,"remaining_time":3.865904577},
{"learn":[0.05426017002],"iteration":412,"passed_time":2.71542506,"remaining_time":3.85945402},
{"learn":[0.05420985596],"iteration":413,"passed_time":2.721553516,"remaining_time":3.852247247},
{"learn":[0.05407819313],"iteration":414,"passed_time":2.727897286,"remaining_time":3.845349186},
{"learn":[0.05397298812],"iteration":415,"passed_time":2.734416791,"remaining_time":3.838700495},
{"learn":[0.05389529579],"iteration":416,"passed_time":2.74054224,"remaining_time":3.831501501},
{"learn":[0.05382181201],"iteration":417,"passed_time":2.746778128,"remaining_time":3.824461413},
{"learn":[0.05374919263],"iteration":418,"passed_time":2.753088197,"remaining_time":3.817528025},
{"learn":[0.05360545011],"iteration":419,"passed_time":2.759571064,"remaining_time":3.810836231},
{"learn":[0.05347015355],"iteration":420,"passed_time":2.765924643,"remaining_time":3.80396762},
{"learn":[0.05336773265],"iteration":421,"passed_time":2.77241016,"remaining_time":3.797282163},
{"learn":[0.05326665895],"iteration":422,"passed_time":2.779320237,"remaining_time":3.791176777},
{"learn":[0.0531995779],"iteration":423,"passed_time":2.785866487,"remaining_time":3.78457334},
{"learn":[0.05305781456],"iteration":424,"passed_time":2.792421971,"remaining_time":3.777982667},
{"learn":[0.05293498993],"iteration":425,"passed_time":2.799396979,"remaining_time":3.771957431},
{"learn":[0.05280440559],"iteration":426,"passed_time":2.806086444,"remaining_time":3.765544573},
{"learn":[0.05265806526],"iteration":427,"passed_time":2.812696297,"remaining_time":3.759024024},
{"learn":[0.0525422788],"iteration":428,"passed_time":2.819497479,"remaining_time":3.752757717},
{"learn":[0.05242786814],"iteration":429,"passed_time":2.826104881,"remaining_time":3.746232052},
{"learn":[0.05233798355],"iteration":430,"passed_time":2.832466156,"remaining_time":3.739381074},
{"learn":[0.05219799838],"iteration":431,"passed_time":2.838680599,"remaining_time":3.732339306},
{"learn":[0.05206036254],"iteration":432,"passed_time":2.845108065,"remaining_time":3.725580307},
{"learn":[0.05188933622],"iteration":433,"passed_time":2.851458849,"remaining_time":3.718722831},
{"learn":[0.05179059889],"iteration":434,"passed_time":2.857723689,"remaining_time":3.711756056},
{"learn":[0.05169926729],"iteration":435,"passed_time":2.863940376,"remaining_time":3.704730211},
{"learn":[0.05159620731],"iteration":436,"passed_time":2.870193788,"remaining_time":3.697755383},
{"learn":[0.05147756445],"iteration":437,"passed_time":2.876571551,"remaining_time":3.690943406},
{"learn":[0.05141193325],"iteration":438,"passed_time":2.882773762,"remaining_time":3.683909068},
{"learn":[0.05134223119],"iteration":439,"passed_time":2.889037216,"remaining_time":3.676956456},
{"learn":[0.05126496199],"iteration":440,"passed_time":2.895317122,"remaining_time":3.670027826},
{"learn":[0.05115036183],"iteration":441,"passed_time":2.901886144,"remaining_time":3.663467123},
{"learn":[0.05105806653],"iteration":442,"passed_time":2.908398816,"remaining_time":3.656835532},
{"learn":[0.05094328193],"iteration":443,"passed_time":2.914808021,"remaining_time":3.65007491},
{"learn":[0.05083390224],"iteration":444,"passed_time":2.921131058,"remaining_time":3.643208398},
{"learn":[0.05076558138],"iteration":445,"passed_time":2.927924651,"remaining_time":3.636928827},
{"learn":[0.05068339617],"iteration":446,"passed_time":2.934227995,"remaining_time":3.63004045},
{"learn":[0.05052314177],"iteration":447,"passed_time":2.940635662,"remaining_time":3.623283226},
{"learn":[0.05039140902],"iteration":448,"passed_time":2.947370461,"remaining_time":3.616929007},
{"learn":[0.05028830431],"iteration":449,"passed_time":2.95383994,"remaining_time":3.610248816},
{"learn":[0.05017653324],"iteration":450,"passed_time":2.960508138,"remaining_time":3.603811458},
{"learn":[0.05006982398],"iteration":451,"passed_time":2.967042963,"remaining_time":3.59721138},
{"learn":[0.04997082344],"iteration":452,"passed_time":2.973502128,"remaining_time":3.59052023},
{"learn":[0.04989195195],"iteration":453,"passed_time":2.979846556,"remaining_time":3.583692113},
{"learn":[0.04976198496],"iteration":454,"passed_time":2.986199315,"remaining_time":3.576876103},
{"learn":[0.04971670452],"iteration":455,"passed_time":2.992469093,"remaining_time":3.569963128},
{"learn":[0.04964026812],"iteration":456,"passed_time":2.998928765,"remaining_time":3.563278598},
{"learn":[0.04957499782],"iteration":457,"passed_time":3.005664654,"remaining_time":3.556921927},
{"learn":[0.04947460575],"iteration":458,"passed_time":3.012421062,"remaining_time":3.550587788},
{"learn":[0.04937952316],"iteration":459,"passed_time":3.019241094,"remaining_time":3.544326502},
{"learn":[0.04931403292],"iteration":460,"passed_time":3.025853747,"remaining_time":3.537820325},
{"learn":[0.04925679397],"iteration":461,"passed_time":3.032211964,"remaining_time":3.531017395},
{"learn":[0.04919979781],"iteration":462,"passed_time":3.038674211,"remaining_time":3.524337044},
{"learn":[0.04909775999],"iteration":463,"passed_time":3.044989541,"remaining_time":3.517487918},
{"learn":[0.04901371648],"iteration":464,"passed_time":3.05142936,"remaining_time":3.510784317},
{"learn":[0.04886663935],"iteration":465,"passed_time":3.057777045,"remaining_time":3.503976271},
{"learn":[0.0487655925],"iteration":466,"passed_time":3.064337229,"remaining_time":3.497412726},
{"learn":[0.04867960807],"iteration":467,"passed_time":3.070645421,"remaining_time":3.490562744},
{"learn":[0.04864361448],"iteration":468,"passed_time":3.077260515,"remaining_time":3.484062544},
{"learn":[0.04856310885],"iteration":469,"passed_time":3.084175062,"remaining_time":3.477899538},
{"learn":[0.04844702772],"iteration":470,"passed_time":3.091136456,"remaining_time":3.471785956},
{"learn":[0.04841140337],"iteration":471,"passed_time":3.097924446,"remaining_time":3.465474804},
{"learn":[0.04833847892],"iteration":472,"passed_time":3.104636225,"remaining_time":3.459076724},
{"learn":[0.04824753371],"iteration":473,"passed_time":3.111079114,"remaining_time":3.452378932},
{"learn":[0.0481378379],"iteration":474,"passed_time":3.117570468,"remaining_time":3.44573578},
{"learn":[0.04809113342],"iteration":475,"passed_time":3.123772964,"remaining_time":3.43877528},
{"learn":[0.0480131034],"iteration":476,"passed_time":3.129999901,"remaining_time":3.431844756},
{"learn":[0.04792274877],"iteration":477,"passed_time":3.136664225,"remaining_time":3.425394823},
{"learn":[0.04778654187],"iteration":478,"passed_time":3.143653512,"remaining_time":3.419297452},
{"learn":[0.04768867591],"iteration":479,"passed_time":3.150338142,"remaining_time":3.41286632},
{"learn":[0.04763344119],"iteration":480,"passed_time":3.156612784,"remaining_time":3.405991756},
{"learn":[0.04754793392],"iteration":481,"passed_time":3.163094856,"remaining_time":3.399342605},
{"learn":[0.04748057078],"iteration":482,"passed_time":3.169590547,"remaining_time":3.392708722},
{"learn":[0.04734305285],"iteration":483,"passed_time":3.176509119,"remaining_time":3.386526251},
{"learn":[0.04725334389],"iteration":484,"passed_time":3.183031785,"remaining_time":3.379920349},
{"learn":[0.04712879653],"iteration":485,"passed_time":3.189550155,"remaining_time":3.373310246},
{"learn":[0.04702491901],"iteration":486,"passed_time":3.195771877,"remaining_time":3.366388035},
{"learn":[0.04696787399],"iteration":487,"passed_time":3.202058716,"remaining_time":3.359537014},
{"learn":[0.04686177622],"iteration":488,"passed_time":3.20838925,"remaining_time":3.352733961},
{"learn":[0.04676091539],"iteration":489,"passed_time":3.215083206,"remaining_time":3.346311092},
{"learn":[0.04670173637],"iteration":490,"passed_time":3.222037816,"remaining_time":3.340157329},
{"learn":[0.04665203227],"iteration":491,"passed_time":3.228276161,"remaining_time":3.333260751},
{"learn":[0.04657839432],"iteration":492,"passed_time":3.234645407,"remaining_time":3.326501463},
{"learn":[0.04653525441],"iteration":493,"passed_time":3.240973756,"remaining_time":3.319701863},
{"learn":[0.04639541661],"iteration":494,"passed_time":3.248250172,"remaining_time":3.313871388},
{"learn":[0.04630302825],"iteration":495,"passed_time":3.255146749,"remaining_time":3.307649116},
{"learn":[0.04627335032],"iteration":496,"passed_time":3.261358319,"remaining_time":3.300730854},
{"learn":[0.04618318712],"iteration":497,"passed_time":3.267748043,"remaining_time":3.293995015},
{"learn":[0.04608535631],"iteration":498,"passed_time":3.274085606,"remaining_time":3.287208193},
{"learn":[0.04601909916],"iteration":499,"passed_time":3.280366989,"remaining_time":3.280366989},
{"learn":[0.0459497683],"iteration":500,"passed_time":3.286635265,"remaining_time":3.273514964},
{"learn":[0.04581704266],"iteration":501,"passed_time":3.293174905,"remaining_time":3.266934468},
{"learn":[0.0456903467],"iteration":502,"passed_time":3.29948682,"remaining_time":3.260129125},
{"learn":[0.04559345898],"iteration":503,"passed_time":3.30595518,"remaining_time":3.253479701},
{"learn":[0.04550643931],"iteration":504,"passed_time":3.3126243,"remaining_time":3.247027779},
{"learn":[0.04541462735],"iteration":505,"passed_time":3.319327377,"remaining_time":3.240608151},
{"learn":[0.04531641908],"iteration":506,"passed_time":3.326202865,"remaining_time":3.234355054},
{"learn":[0.04519127094],"iteration":507,"passed_time":3.333084857,"remaining_time":3.228105806},
{"learn":[0.04511150952],"iteration":508,"passed_time":3.339730094,"remaining_time":3.22162569},
{"learn":[0.04502256019],"iteration":509,"passed_time":3.346153642,"remaining_time":3.214931931},
{"learn":[0.0449237333],"iteration":510,"passed_time":3.352575281,"remaining_time":3.208237402},
{"learn":[0.04483946108],"iteration":511,"passed_time":3.3590608,"remaining_time":3.201604825},
{"learn":[0.04477151158],"iteration":512,"passed_time":3.365423133,"remaining_time":3.194855879},
{"learn":[0.04468887057],"iteration":513,"passed_time":3.37217133,"remaining_time":3.188473281},
{"learn":[0.04456587551],"iteration":514,"passed_time":3.379076691,"remaining_time":3.182237273},
{"learn":[0.04449968335],"iteration":515,"passed_time":3.385612816,"remaining_time":3.175652331},
{"learn":[0.04446894959],"iteration":516,"passed_time":3.392037335,"remaining_time":3.168963313},
{"learn":[0.04443002003],"iteration":517,"passed_time":3.398255622,"remaining_time":3.162083416},
{"learn":[0.04434852098],"iteration":518,"passed_time":3.404552829,"remaining_time":3.155279212},
{"learn":[0.04427133142],"iteration":519,"passed_time":3.411101071,"remaining_time":3.148708681},
{"learn":[0.04417656974],"iteration":520,"passed_time":3.417172239,"remaining_time":3.141699621},
{"learn":[0.0441126671],"iteration":521,"passed_time":3.423439826,"remaining_time":3.134874017},
{"learn":[0.04407880633],"iteration":522,"passed_time":3.429654042,"remaining_time":3.12800187},
{"learn":[0.04398841006],"iteration":523,"passed_time":3.436498674,"remaining_time":3.121704903},
{"learn":[0.04390503976],"iteration":524,"passed_time":3.443090613,"remaining_time":3.115177221},
{"learn":[0.04381541517],"iteration":525,"passed_time":3.449690173,"remaining_time":3.108656164},
{"learn":[0.04377312322],"iteration":526,"passed_time":3.455993354,"remaining_time":3.101868798},
{"learn":[0.04370040461],"iteration":527,"passed_time":3.462454682,"remaining_time":3.09522464},
{"learn":[0.043588672],"iteration":528,"passed_time":3.46878826,"remaining_time":3.08846743},
{"learn":[0.04352018589],"iteration":529,"passed_time":3.475269765,"remaining_time":3.081843},
{"learn":[0.04342878256],"iteration":530,"passed_time":3.481690163,"remaining_time":3.075165135},
{"learn":[0.04338320346],"iteration":531,"passed_time":3.48786091,"remaining_time":3.06826862},
{"learn":[0.0433020642],"iteration":532,"passed_time":3.494269258,"remaining_time":3.061583009},
{"learn":[0.04322128364],"iteration":533,"passed_time":3.500565945,"remaining_time":3.054800993},
{"learn":[0.04314129751],"iteration":534,"passed_time":3.507010517,"remaining_time":3.048149328},
{"learn":[0.04297185496],"iteration":535,"passed_time":3.513398847,"remaining_time":3.041449748},
{"learn":[0.04284057946],"iteration":536,"passed_time":3.519794484,"remaining_time":3.034757628},
{"learn":[0.04281539315],"iteration":537,"passed_time":3.525852131,"remaining_time":3.027776365},
{"learn":[0.04268123896],"iteration":538,"passed_time":3.532346786,"remaining_time":3.021172298},
{"learn":[0.0426205615],"iteration":539,"passed_time":3.538644041,"remaining_time":3.014400479},
{"learn":[0.04251436055],"iteration":540,"passed_time":3.544951475,"remaining_time":3.007639052},
{"learn":[0.04245979247],"iteration":541,"passed_time":3.551242405,"remaining_time":3.000865353},
{"learn":[0.04235267716],"iteration":542,"passed_time":3.557494597,"remaining_time":2.99406083},
{"learn":[0.04225152867],"iteration":543,"passed_time":3.564001445,"remaining_time":2.987471799},
{"learn":[0.04219012746],"iteration":544,"passed_time":3.570277129,"remaining_time":2.98069008},
{"learn":[0.04211235437],"iteration":545,"passed_time":3.576726131,"remaining_time":2.974054329},
{"learn":[0.0420247218],"iteration":546,"passed_time":3.582888876,"remaining_time":2.967182195},
{"learn":[0.04186268902],"iteration":547,"passed_time":3.589579109,"remaining_time":2.960747732},
{"learn":[0.04179368759],"iteration":548,"passed_time":3.59592644,"remaining_time":2.954030645},
{"learn":[0.0417676486],"iteration":549,"passed_time":3.60202014,"remaining_time":2.947107387},
{"learn":[0.04172824536],"iteration":550,"passed_time":3.608333286,"remaining_time":2.940365963},
{"learn":[0.04164242105],"iteration":551,"passed_time":3.614673001,"remaining_time":2.933647653},
{"learn":[0.04157410221],"iteration":552,"passed_time":3.621000651,"remaining_time":2.92692096},
{"learn":[0.04150325986],"iteration":553,"passed_time":3.627132812,"remaining_time":2.920038329},
{"learn":[0.04142620694],"iteration":554,"passed_time":3.633361226,"remaining_time":2.913235578},
{"learn":[0.04140335777],"iteration":555,"passed_time":3.639555148,"remaining_time":2.906407348},
{"learn":[0.04133969033],"iteration":556,"passed_time":3.645990643,"remaining_time":2.899773527},
{"learn":[0.04130482778],"iteration":557,"passed_time":3.65200962,"remaining_time":2.892810487},
{"learn":[0.04122291566],"iteration":558,"passed_time":3.658481895,"remaining_time":2.886208436},
{"learn":[0.04116101529],"iteration":559,"passed_time":3.664783364,"remaining_time":2.879472643},
{"learn":[0.04107881817],"iteration":560,"passed_time":3.671125805,"remaining_time":2.87277046},
{"learn":[0.04104271555],"iteration":561,"passed_time":3.677298495,"remaining_time":2.865937261},
{"learn":[0.04098389526],"iteration":562,"passed_time":3.683923323,"remaining_time":2.859457357},
{"learn":[0.04085298833],"iteration":563,"passed_time":3.690774889,"remaining_time":2.853152219},
{"learn":[0.04083426726],"iteration":564,"passed_time":3.69732623,"remaining_time":2.846614},
{"learn":[0.04072937149],"iteration":565,"passed_time":3.703840979,"remaining_time":2.840047676},
{"learn":[0.0406268887],"iteration":566,"passed_time":3.71065237,"remaining_time":2.833708071},
{"learn":[0.04056592454],"iteration":567,"passed_time":3.717153178,"remaining_time":2.827130586},
{"learn":[0.0405094873],"iteration":568,"passed_time":3.723277307,"remaining_time":2.820268048},
{"learn":[0.04043653142],"iteration":569,"passed_time":3.729667389,"remaining_time":2.813608732},
{"learn":[0.04039021771],"iteration":570,"passed_time":3.735887887,"remaining_time":2.806822948},
{"learn":[0.04028673439],"iteration":571,"passed_time":3.742442025,"remaining_time":2.800288788},
{"learn":[0.04018072141],"iteration":572,"passed_time":3.748763103,"remaining_time":2.793580882},
{"learn":[0.04006521493],"iteration":573,"passed_time":3.755163406,"remaining_time":2.78693312},
{"learn":[0.0399859553],"iteration":574,"passed_time":3.761570423,"remaining_time":2.780291182},
{"learn":[0.03991148884],"iteration":575,"passed_time":3.768086009,"remaining_time":2.773729979},
{"learn":[0.03983852278],"iteration":576,"passed_time":3.77438337,"remaining_time":2.767008952},
{"learn":[0.03975148255],"iteration":577,"passed_time":3.780897948,"remaining_time":2.760447983},
{"learn":[0.03972658303],"iteration":578,"passed_time":3.787296404,"remaining_time":2.753802739},
{"learn":[0.03966091265],"iteration":579,"passed_time":3.793607027,"remaining_time":2.747094743},
{"learn":[0.03958600289],"iteration":580,"passed_time":3.800069833,"remaining_time":2.740497866},
{"learn":[0.03952984933],"iteration":581,"passed_time":3.806410465,"remaining_time":2.733813701},
{"learn":[0.03950460757],"iteration":582,"passed_time":3.812635504,"remaining_time":2.727048036},
{"learn":[0.03943537094],"iteration":583,"passed_time":3.818982938,"remaining_time":2.720371408},
{"learn":[0.03936549244],"iteration":584,"passed_time":3.825598758,"remaining_time":2.713886298},
{"learn":[0.03928863872],"iteration":585,"passed_time":3.832003621,"remaining_time":2.707251705},
{"learn":[0.0392254959],"iteration":586,"passed_time":3.838485858,"remaining_time":2.700672333},
{"learn":[0.03912369249],"iteration":587,"passed_time":3.8448681,"remaining_time":2.694023226},
{"learn":[0.03904203527],"iteration":588,"passed_time":3.851191789,"remaining_time":2.687334168},
{"learn":[0.03900648278],"iteration":589,"passed_time":3.857628531,"remaining_time":2.680724911},
{"learn":[0.03893452686],"iteration":590,"passed_time":3.863901231,"remaining_time":2.674002713},
{"learn":[0.03886352176],"iteration":591,"passed_time":3.870341712,"remaining_time":2.667397666},
{"learn":[0.03880272083],"iteration":592,"passed_time":3.876890955,"remaining_time":2.660867822},
{"learn":[0.03869426237],"iteration":593,"passed_time":3.883121256,"remaining_time":2.654119915},
{"learn":[0.0386221767],"iteration":594,"passed_time":3.889623994,"remaining_time":2.647559189},
{"learn":[0.03852295834],"iteration":595,"passed_time":3.896187669,"remaining_time":2.641039964},
{"learn":[0.03845223207],"iteration":596,"passed_time":3.903016917,"remaining_time":2.634699862},
{"learn":[0.03833059303],"iteration":597,"passed_time":3.909785305,"remaining_time":2.628317212},
{"learn":[0.03827513628],"iteration":598,"passed_time":3.916479991,"remaining_time":2.621883934},
{"learn":[0.03820610208],"iteration":599,"passed_time":3.922681776,"remaining_time":2.615121184},
{"learn":[0.03812709894],"iteration":600,"passed_time":3.929190553,"remaining_time":2.608564111},
{"learn":[0.03806877594],"iteration":601,"passed_time":3.935405039,"remaining_time":2.601812634},
{"learn":[0.0379772915],"iteration":602,"passed_time":3.941847491,"remaining_time":2.595213025},
{"learn":[0.03796102458],"iteration":603,"passed_time":3.948221858,"remaining_time":2.588569297},
{"learn":[0.0379137051],"iteration":604,"passed_time":3.954297502,"remaining_time":2.581731427},
{"learn":[0.03786278161],"iteration":605,"passed_time":3.960619949,"remaining_time":2.575056534},
{"learn":[0.0377649056],"iteration":606,"passed_time":3.967182024,"remaining_time":2.56853795},
{"learn":[0.03769989898],"iteration":607,"passed_time":3.9735236,"remaining_time":2.561877058},
{"learn":[0.03766175373],"iteration":608,"passed_time":3.980044972,"remaining_time":2.555332651},
{"learn":[0.03760322969],"iteration":609,"passed_time":3.986111422,"remaining_time":2.548497466},
{"learn":[0.03758548321],"iteration":610,"passed_time":3.992371317,"remaining_time":2.541787958},
{"learn":[0.03753812127],"iteration":611,"passed_time":3.999112288,"remaining_time":2.535384914},
{"learn":[0.03749140425],"iteration":612,"passed_time":4.005809845,"remaining_time":2.528953361},
{"learn":[0.03741004828],"iteration":613,"passed_time":4.012485344,"remaining_time":2.522507073},
{"learn":[0.03734850364],"iteration":614,"passed_time":4.018890231,"remaining_time":2.515890633},
{"learn":[0.03731557886],"iteration":615,"passed_time":4.025180754,"remaining_time":2.509203587},
{"learn":[0.03724361803],"iteration":616,"passed_time":4.031607216,"remaining_time":2.50260221},
{"learn":[0.0371892701],"iteration":617,"passed_time":4.038240311,"remaining_time":2.496129124},
{"learn":[0.03713553285],"iteration":618,"passed_time":4.044860487,"remaining_time":2.48964757},
{"learn":[0.0370812527],"iteration":619,"passed_time":4.05163087,"remaining_time":2.48325763},
{"learn":[0.03699828244],"iteration":620,"passed_time":4.05839362,"remaining_time":2.476861807},
{"learn":[0.03695289509],"iteration":621,"passed_time":4.064639321,"remaining_time":2.470150584},
{"learn":[0.03688587167],"iteration":622,"passed_time":4.070998221,"remaining_time":2.463509357},
{"learn":[0.03679538693],"iteration":623,"passed_time":4.077550817,"remaining_time":2.456985749},
{"learn":[0.03674826592],"iteration":624,"passed_time":4.083591533,"remaining_time":2.45015492},
{"learn":[0.03668705528],"iteration":625,"passed_time":4.090015063,"remaining_time":2.443555325},
{"learn":[0.0366312211],"iteration":626,"passed_time":4.096714303,"remaining_time":2.437120311},
{"learn":[0.03655505079],"iteration":627,"passed_time":4.103517508,"remaining_time":2.43074604},
{"learn":[0.03652066306],"iteration":628,"passed_time":4.110326381,"remaining_time":2.424373748},
{"learn":[0.03645868227],"iteration":629,"passed_time":4.117662093,"remaining_time":2.418309483},
{"learn":[0.0364000239],"iteration":630,"passed_time":4.12467266,"remaining_time":2.412051048},
{"learn":[0.03633201264],"iteration":631,"passed_time":4.131138951,"remaining_time":2.405473313},
{"learn":[0.03628261012],"iteration":632,"passed_time":4.137468525,"remaining_time":2.398816665},
{"learn":[0.03621377603],"iteration":633,"passed_time":4.144050664,"remaining_time":2.39230685},
{"learn":[0.0361880966],"iteration":634,"passed_time":4.150210091,"remaining_time":2.385553832},
{"learn":[0.03610661788],"iteration":635,"passed_time":4.156624488,"remaining_time":2.378948607},
{"learn":[0.03607610023],"iteration":636,"passed_time":4.163205356,"remaining_time":2.372438845},
{"learn":[0.03605205747],"iteration":637,"passed_time":4.169415552,"remaining_time":2.365718542},
{"learn":[0.0360196315],"iteration":638,"passed_time":4.175608948,"remaining_time":2.358990345},
{"learn":[0.03595627207],"iteration":639,"passed_time":4.182290487,"remaining_time":2.352538399},
{"learn":[0.03588402953],"iteration":640,"passed_time":4.188552551,"remaining_time":2.345850805},
{"learn":[0.03579847811],"iteration":641,"passed_time":4.195086186,"remaining_time":2.339315973},
{"learn":[0.03571094441],"iteration":642,"passed_time":4.201487241,"remaining_time":2.332707535},
{"learn":[0.03566252646],"iteration":643,"passed_time":4.207980883,"remaining_time":2.326150923},
{"learn":[0.0355982867],"iteration":644,"passed_time":4.214323089,"remaining_time":2.319511158},
{"learn":[0.03554783056],"iteration":645,"passed_time":4.220951828,"remaining_time":2.31302933},
{"learn":[0.03549766059],"iteration":646,"passed_time":4.227487783,"remaining_time":2.306496426},
{"learn":[0.03540471647],"iteration":647,"passed_time":4.234378335,"remaining_time":2.300156133},
{"learn":[0.03532841165],"iteration":648,"passed_time":4.241164027,"remaining_time":2.293757432},
{"learn":[0.0352860367],"iteration":649,"passed_time":4.247558688,"remaining_time":2.287146986},
{"learn":[0.03520216989],"iteration":650,"passed_time":4.253920496,"remaining_time":2.28051959},
{"learn":[0.03511919142],"iteration":651,"passed_time":4.260394163,"remaining_time":2.273952713},
{"learn":[0.03504645076],"iteration":652,"passed_time":4.26683521,"remaining_time":2.267368787},
{"learn":[0.03502075671],"iteration":653,"passed_time":4.273127772,"remaining_time":2.260706742},
{"learn":[0.0349860302],"iteration":654,"passed_time":4.279241575,"remaining_time":2.253951669},
{"learn":[0.03493347034],"iteration":655,"passed_time":4.285746971,"remaining_time":2.2474039},
{"learn":[0.03487981533],"iteration":656,"passed_time":4.292337877,"remaining_time":2.240900901},
{"learn":[0.03483180103],"iteration":657,"passed_time":4.299002246,"remaining_time":2.234435818},
{"learn":[0.03477580524],"iteration":658,"passed_time":4.305575491,"remaining_time":2.227922978},
{"learn":[0.0346988955],"iteration":659,"passed_time":4.312160705,"remaining_time":2.221416121},
{"learn":[0.03462177355],"iteration":660,"passed_time":4.318661277,"remaining_time":2.214865617},
{"learn":[0.03456811031],"iteration":661,"passed_time":4.32493885,"remaining_time":2.208201407},
{"learn":[0.03451520048],"iteration":662,"passed_time":4.331261781,"remaining_time":2.201561418},
{"learn":[0.03442944063],"iteration":663,"passed_time":4.337974036,"remaining_time":2.195119392},
{"learn":[0.03434668163],"iteration":664,"passed_time":4.344719315,"remaining_time":2.188693189},
{"learn":[0.0342920642],"iteration":665,"passed_time":4.351099276,"remaining_time":2.18208282},
{"learn":[0.03422213481],"iteration":666,"passed_time":4.357652895,"remaining_time":2.175559841},
{"learn":[0.03420487438],"iteration":667,"passed_time":4.363792098,"remaining_time":2.168830803},
{"learn":[0.03415974653],"iteration":668,"passed_time":4.369983614,"remaining_time":2.162129412},
{"learn":[0.0340915973],"iteration":669,"passed_time":4.376330563,"remaining_time":2.155506098},
{"learn":[0.03406032867],"iteration":670,"passed_time":4.382483673,"remaining_time":2.148788567},
{"learn":[0.03399267943],"iteration":671,"passed_time":4.38893937,"remaining_time":2.142220407},
{"learn":[0.03395322693],"iteration":672,"passed_time":4.39516028,"remaining_time":2.135538502},
{"learn":[0.03390038328],"iteration":673,"passed_time":4.401382857,"remaining_time":2.12885877},
{"learn":[0.03380639995],"iteration":674,"passed_time":4.407808584,"remaining_time":2.122278207},
{"learn":[0.03379221942],"iteration":675,"passed_time":4.413867296,"remaining_time":2.115522195},
{"learn":[0.03373415046],"iteration":676,"passed_time":4.420076724,"remaining_time":2.108840151},
{"learn":[0.03366828219],"iteration":677,"passed_time":4.426614458,"remaining_time":2.102315421},
{"learn":[0.03363670955],"iteration":678,"passed_time":4.432754843,"remaining_time":2.095602805},
{"learn":[0.03359406508],"iteration":679,"passed_time":4.439015398,"remaining_time":2.088948423},
{"learn":[0.03354192303],"iteration":680,"passed_time":4.445271654,"remaining_time":2.082293183},
{"learn":[0.03349692866],"iteration":681,"passed_time":4.451744883,"remaining_time":2.075740283},
{"learn":[0.03341565849],"iteration":682,"passed_time":4.458380864,"remaining_time":2.069263153},
{"learn":[0.03337356553],"iteration":683,"passed_time":4.464744557,"remaining_time":2.062659766},
{"learn":[0.03328994991],"iteration":684,"passed_time":4.471372816,"remaining_time":2.05617874},
{"learn":[0.03323370894],"iteration":685,"passed_time":4.47788444,"remaining_time":2.049643898},
{"learn":[0.03314596109],"iteration":686,"passed_time":4.484490537,"remaining_time":2.043152166},
{"learn":[0.03310113188],"iteration":687,"passed_time":4.490807094,"remaining_time":2.036528798},
{"learn":[0.03301544998],"iteration":688,"passed_time":4.497492692,"remaining_time":2.030072899},
{"learn":[0.03295898712],"iteration":689,"passed_time":4.504310367,"remaining_time":2.023675672},
{"learn":[0.03291723748],"iteration":690,"passed_time":4.510959516,"remaining_time":2.017201868},
{"learn":[0.03284950689],"iteration":691,"passed_time":4.517959185,"remaining_time":2.010883568},
{"learn":[0.03278641725],"iteration":692,"passed_time":4.524786029,"remaining_time":2.00448674},
{"learn":[0.0327139478],"iteration":693,"passed_time":4.531142101,"remaining_time":1.997881099},
{"learn":[0.03268768186],"iteration":694,"passed_time":4.537430281,"remaining_time":1.991246383},
{"learn":[0.03263551917],"iteration":695,"passed_time":4.543614731,"remaining_time":1.984567354},
{"learn":[0.03259298248],"iteration":696,"passed_time":4.549894758,"remaining_time":1.977931293},
{"learn":[0.03255157709],"iteration":697,"passed_time":4.556284724,"remaining_time":1.97134382},
{"learn":[0.03250761389],"iteration":698,"passed_time":4.562814871,"remaining_time":1.964817276},
{"learn":[0.03244762637],"iteration":699,"passed_time":4.56957351,"remaining_time":1.958388647},
{"learn":[0.03241229037],"iteration":700,"passed_time":4.57589702,"remaining_time":1.951773479},
{"learn":[0.03236057719],"iteration":701,"passed_time":4.582163217,"remaining_time":1.945134813},
{"learn":[0.03227465101],"iteration":702,"passed_time":4.588754093,"remaining_time":1.938634375},
{"learn":[0.03224386067],"iteration":703,"passed_time":4.594891757,"remaining_time":1.931943125},
{"learn":[0.03216827962],"iteration":704,"passed_time":4.601499579,"remaining_time":1.925450178},
{"learn":[0.03213727003],"iteration":705,"passed_time":4.608231709,"remaining_time":1.919008672},
{"learn":[0.03209109904],"iteration":706,"passed_time":4.614861318,"remaining_time":1.912523856},
{"learn":[0.0320519162],"iteration":707,"passed_time":4.621306314,"remaining_time":1.905962491},
{"learn":[0.03201685202],"iteration":708,"passed_time":4.627580372,"remaining_time":1.899331295},
{"learn":[0.03195390964],"iteration":709,"passed_time":4.634270654,"remaining_time":1.892871112},
{"learn":[0.03191062183],"iteration":710,"passed_time":4.640500804,"remaining_time":1.886223252},
{"learn":[0.03187111585],"iteration":711,"passed_time":4.647094346,"remaining_time":1.879723556},
{"learn":[0.03179972188],"iteration":712,"passed_time":4.653912194,"remaining_time":1.873313884},
{"learn":[0.03173280955],"iteration":713,"passed_time":4.660590688,"remaining_time":1.86684725},
{"learn":[0.03169412561],"iteration":714,"passed_time":4.667085518,"remaining_time":1.860306815},
{"learn":[0.03165110176],"iteration":715,"passed_time":4.673741982,"remaining_time":1.853830619},
{"learn":[0.03159580101],"iteration":716,"passed_time":4.680456048,"remaining_time":1.847376655},
{"learn":[0.03158082399],"iteration":717,"passed_time":4.686706641,"remaining_time":1.840739934},
{"learn":[0.03153478968],"iteration":718,"passed_time":4.693555509,"remaining_time":1.834338106},
{"learn":[0.03149489193],"iteration":719,"passed_time":4.700162666,"remaining_time":1.827841037},
{"learn":[0.03140663124],"iteration":720,"passed_time":4.706751013,"remaining_time":1.821336384},
{"learn":[0.03136516713],"iteration":721,"passed_time":4.713661355,"remaining_time":1.81495548},
{"learn":[0.03131930177],"iteration":722,"passed_time":4.720308178,"remaining_time":1.808472151},
{"learn":[0.03127588068],"iteration":723,"passed_time":4.727092939,"remaining_time":1.802040955},
{"learn":[0.0312353219],"iteration":724,"passed_time":4.733541706,"remaining_time":1.795481337},
{"learn":[0.03121417472],"iteration":725,"passed_time":4.739879976,"remaining_time":1.788880321},
{"learn":[0.03113718952],"iteration":726,"passed_time":4.746606637,"remaining_time":1.782425876},
{"learn":[0.03110837145],"iteration":727,"passed_time":4.752820718,"remaining_time":1.775779169},
{"learn":[0.03107325364],"iteration":728,"passed_time":4.759118592,"remaining_time":1.769164799},
{"learn":[0.0310197005],"iteration":729,"passed_time":4.765489141,"remaining_time":1.762578176},
{"learn":[0.03097084387],"iteration":730,"passed_time":4.771573679,"remaining_time":1.755886894},
{"learn":[0.0309015333],"iteration":731,"passed_time":4.778188107,"remaining_time":1.749391274},
{"learn":[0.03089164294],"iteration":732,"passed_time":4.784436643,"remaining_time":1.742762051},
{"learn":[0.03086537472],"iteration":733,"passed_time":4.790667404,"remaining_time":1.736127424},
{"learn":[0.03084886397],"iteration":734,"passed_time":4.796691171,"remaining_time":1.729419266},
{"learn":[0.0308041599],"iteration":735,"passed_time":4.803099374,"remaining_time":1.722850862},
{"learn":[0.03076460783],"iteration":736,"passed_time":4.809293428,"remaining_time":1.716206474},
{"learn":[0.03073872895],"iteration":737,"passed_time":4.815728272,"remaining_time":1.709648791},
{"learn":[0.03068858831],"iteration":738,"passed_time":4.822187118,"remaining_time":1.703099916},
{"learn":[0.03062151336],"iteration":739,"passed_time":4.828920873,"remaining_time":1.696647874},
{"learn":[0.03056277721],"iteration":740,"passed_time":4.835335952,"remaining_time":1.690083686},
{"learn":[0.03052546943],"iteration":741,"passed_time":4.841846937,"remaining_time":1.683553248},
{"learn":[0.03047907251],"iteration":742,"passed_time":4.84812802,"remaining_time":1.676943339},
{"learn":[0.03043015597],"iteration":743,"passed_time":4.854704184,"remaining_time":1.670435848},
{"learn":[0.0303984576],"iteration":744,"passed_time":4.861335027,"remaining_time":1.663946888},
{"learn":[0.03035013464],"iteration":745,"passed_time":4.867862606,"remaining_time":1.657422389},
{"learn":[0.03029726257],"iteration":746,"passed_time":4.874661884,"remaining_time":1.650989902},
{"learn":[0.03026381929],"iteration":747,"passed_time":4.881209949,"remaining_time":1.644471801},
{"learn":[0.03021338825],"iteration":748,"passed_time":4.888088135,"remaining_time":1.638064248},
{"learn":[0.03013068622],"iteration":749,"passed_time":4.895027423,"remaining_time":1.631675808},
{"learn":[0.03008946658],"iteration":750,"passed_time":4.901608727,"remaining_time":1.625167208},
{"learn":[0.03004037352],"iteration":751,"passed_time":4.908103104,"remaining_time":1.618629747},
{"learn":[0.03001101891],"iteration":752,"passed_time":4.914840872,"remaining_time":1.612172238},
{"learn":[0.02995105082],"iteration":753,"passed_time":4.921634525,"remaining_time":1.605732219},
{"learn":[0.02993591657],"iteration":754,"passed_time":4.928459873,"remaining_time":1.599301548},
{"learn":[0.02987672571],"iteration":755,"passed_time":4.935274305,"remaining_time":1.59286631},
{"learn":[0.02983590705],"iteration":756,"passed_time":4.941831216,"remaining_time":1.586347405},
{"learn":[0.02978497465],"iteration":757,"passed_time":4.94873139,"remaining_time":1.57993799},
{"learn":[0.02974243934],"iteration":758,"passed_time":4.955480799,"remaining_time":1.573479411},
{"learn":[0.02972921507],"iteration":759,"passed_time":4.962195179,"remaining_time":1.567009004},
{"learn":[0.02965977667],"iteration":760,"passed_time":4.968894797,"remaining_time":1.56053332},
{"learn":[0.02959550071],"iteration":761,"passed_time":4.97539522,"remaining_time":1.553994833},
{"learn":[0.0295429193],"iteration":762,"passed_time":4.981827331,"remaining_time":1.547435226},
{"learn":[0.02948647034],"iteration":763,"passed_time":4.988476837,"remaining_time":1.540943107},
{"learn":[0.02946633664],"iteration":764,"passed_time":4.994831126,"remaining_time":1.534359888},
{"learn":[0.02943476416],"iteration":765,"passed_time":5.001548407,"remaining_time":1.527888156},
{"learn":[0.02941163369],"iteration":766,"passed_time":5.008155592,"remaining_time":1.521382338},
{"learn":[0.02937833837],"iteration":767,"passed_time":5.014914346,"remaining_time":1.514922042},
{"learn":[0.0293381846],"iteration":768,"passed_time":5.021830043,"remaining_time":1.508508114},
{"learn":[0.02931272977],"iteration":769,"passed_time":5.028087947,"remaining_time":1.5018964},
{"learn":[0.02926972387],"iteration":770,"passed_time":5.034630157,"remaining_time":1.495370047},
{"learn":[0.02923725301],"iteration":771,"passed_time":5.040896512,"remaining_time":1.488762182},
{"learn":[0.02920604455],"iteration":772,"passed_time":5.046980082,"remaining_time":1.482101525},
{"learn":[0.02917022718],"iteration":773,"passed_time":5.053119792,"remaining_time":1.475458751},
{"learn":[0.02913975333],"iteration":774,"passed_time":5.059466525,"remaining_time":1.468877378},
{"learn":[0.02910166508],"iteration":775,"passed_time":5.065703276,"remaining_time":1.462264863},
{"learn":[0.02906810046],"iteration":776,"passed_time":5.071934933,"remaining_time":1.455651853},
{"learn":[0.02905520168],"iteration":777,"passed_time":5.078137588,"remaining_time":1.449031548},
{"learn":[0.02900200488],"iteration":778,"passed_time":5.08441051,"remaining_time":1.44243225},
{"learn":[0.02896379014],"iteration":779,"passed_time":5.090757062,"remaining_time":1.435854556},
{"learn":[0.02891212941],"iteration":780,"passed_time":5.09729103,"remaining_time":1.429330007},
{"learn":[0.02889644317],"iteration":781,"passed_time":5.103967894,"remaining_time":1.42284527},
{"learn":[0.02884552391],"iteration":782,"passed_time":5.111097786,"remaining_time":1.416485593},
{"learn":[0.02879178328],"iteration":783,"passed_time":5.117323325,"remaining_time":1.409874794},
{"learn":[0.02877980736],"iteration":784,"passed_time":5.123416675,"remaining_time":1.403228771},
{"learn":[0.02872521679],"iteration":785,"passed_time":5.130052213,"remaining_time":1.396731773},
{"learn":[0.02867365801],"iteration":786,"passed_time":5.136468569,"remaining_time":1.390175102},
{"learn":[0.02862664113],"iteration":787,"passed_time":5.143028249,"remaining_time":1.383657346},
{"learn":[0.02858933075],"iteration":788,"passed_time":5.149359978,"remaining_time":1.377078524},
{"learn":[0.0285648749],"iteration":789,"passed_time":5.15613835,"remaining_time":1.370619055},
{"learn":[0.02853169693],"iteration":790,"passed_time":5.162882266,"remaining_time":1.364149676},
{"learn":[0.0284928537],"iteration":791,"passed_time":5.169592607,"remaining_time":1.357670786},
{"learn":[0.02847009384],"iteration":792,"passed_time":5.176282049,"remaining_time":1.351185857},
{"learn":[0.02845124194],"iteration":793,"passed_time":5.182902325,"remaining_time":1.344682467},
{"learn":[0.02840487841],"iteration":794,"passed_time":5.189375153,"remaining_time":1.338140763},
{"learn":[0.02835160742],"iteration":795,"passed_time":5.196120682,"remaining_time":1.331669119},
{"learn":[0.02832612634],"iteration":796,"passed_time":5.202674321,"remaining_time":1.325147914},
{"learn":[0.02829977501],"iteration":797,"passed_time":5.209300271,"remaining_time":1.318644931},
{"learn":[0.02827352592],"iteration":798,"passed_time":5.215873424,"remaining_time":1.312128358},
{"learn":[0.02821274028],"iteration":799,"passed_time":5.222534834,"remaining_time":1.305633708},
{"learn":[0.02819141413],"iteration":800,"passed_time":5.2289607,"remaining_time":1.299080124},
{"learn":[0.02815830779],"iteration":801,"passed_time":5.235402306,"remaining_time":1.292530744},
{"learn":[0.02811432224],"iteration":802,"passed_time":5.241896265,"remaining_time":1.285994476},
{"learn":[0.0280685315],"iteration":803,"passed_time":5.248300237,"remaining_time":1.279436376},
{"learn":[0.02800930683],"iteration":804,"passed_time":5.254988146,"remaining_time":1.272947439},
{"learn":[0.02794843999],"iteration":805,"passed_time":5.261416943,"remaining_time":1.266395641},
{"learn":[0.0279182019],"iteration":806,"passed_time":5.267750901,"remaining_time":1.259821467},
{"learn":[0.0278431402],"iteration":807,"passed_time":5.274640538,"remaining_time":1.25337993},
{"learn":[0.0277995554],"iteration":808,"passed_time":5.280862379,"remaining_time":1.246779622},
{"learn":[0.02776017967],"iteration":809,"passed_time":5.28722683,"remaining_time":1.240213701},
{"learn":[0.02772675326],"iteration":810,"passed_time":5.29352235,"remaining_time":1.233632212},
{"learn":[0.0276900929],"iteration":811,"passed_time":5.299954394,"remaining_time":1.227083037},
{"learn":[0.02765959102],"iteration":812,"passed_time":5.306540819,"remaining_time":1.22056966},
{"learn":[0.02761957394],"iteration":813,"passed_time":5.312873602,"remaining_time":1.213998145},
{"learn":[0.02755750155],"iteration":814,"passed_time":5.319581585,"remaining_time":1.207512384},
{"learn":[0.02754947283],"iteration":815,"passed_time":5.325690625,"remaining_time":1.200891023},
{"learn":[0.02752655021],"iteration":816,"passed_time":5.331927938,"remaining_time":1.194299648},
{"learn":[0.02745918484],"iteration":817,"passed_time":5.338566923,"remaining_time":1.187798509},
{"learn":[0.02741958261],"iteration":818,"passed_time":5.344862961,"remaining_time":1.181221241},
{"learn":[0.02739350248],"iteration":819,"passed_time":5.351375857,"remaining_time":1.174692261},
{"learn":[0.02738465195],"iteration":820,"passed_time":5.357497202,"remaining_time":1.168077953},
{"learn":[0.02737605779],"iteration":821,"passed_time":5.363970908,"remaining_time":1.161541145},
{"learn":[0.02734822607],"iteration":822,"passed_time":5.370753052,"remaining_time":1.155070827},
{"learn":[0.02728686655],"iteration":823,"passed_time":5.377756009,"remaining_time":1.148646915},
{"learn":[0.02725229266],"iteration":824,"passed_time":5.384259622,"remaining_time":1.142115677},
{"learn":[0.02721749133],"iteration":825,"passed_time":5.390477937,"remaining_time":1.135524408},
{"learn":[0.02718154305],"iteration":826,"passed_time":5.397082688,"remaining_time":1.129014879},
{"learn":[0.02715607441],"iteration":827,"passed_time":5.403827567,"remaining_time":1.122534229},
{"learn":[0.02711883448],"iteration":828,"passed_time":5.41052779,"remaining_time":1.11604373},
{"learn":[0.02708087526],"iteration":829,"passed_time":5.417263455,"remaining_time":1.109559985},
{"learn":[0.02704942246],"iteration":830,"passed_time":5.423971497,"remaining_time":1.103070016},
{"learn":[0.02701621038],"iteration":831,"passed_time":5.430505639,"remaining_time":1.096544408},
{"learn":[0.02698979105],"iteration":832,"passed_time":5.436982779,"remaining_time":1.090007352},
{"learn":[0.02694970501],"iteration":833,"passed_time":5.443425785,"remaining_time":1.083463645},
{"learn":[0.02691898828],"iteration":834,"passed_time":5.449452449,"remaining_time":1.076837909},
{"learn":[0.02686963005],"iteration":835,"passed_time":5.456040687,"remaining_time":1.070323771},
{"learn":[0.02683939605],"iteration":836,"passed_time":5.462350893,"remaining_time":1.063755311},
{"learn":[0.02679935204],"iteration":837,"passed_time":5.468733912,"remaining_time":1.057201544},
{"learn":[0.02676180333],"iteration":838,"passed_time":5.474875506,"remaining_time":1.050601855},
{"learn":[0.02669800207],"iteration":839,"passed_time":5.481426522,"remaining_time":1.044081242},
{"learn":[0.02665160049],"iteration":840,"passed_time":5.4877169,"remaining_time":1.037511281},
{"learn":[0.02662104421],"iteration":841,"passed_time":5.494020104,"remaining_time":1.03094439},
{"learn":[0.02657685996],"iteration":842,"passed_time":5.500575773,"remaining_time":1.024425144},
{"learn":[0.02653686889],"iteration":843,"passed_time":5.507231076,"remaining_time":1.017924227},
{"learn":[0.02649320786],"iteration":844,"passed_time":5.513888034,"remaining_time":1.011423249},
{"learn":[0.02646068099],"iteration":845,"passed_time":5.520484956,"remaining_time":1.004910973},
{"learn":[0.02641989867],"iteration":846,"passed_time":5.526996509,"remaining_time":0.9983830765},
{"learn":[0.02638598329],"iteration":847,"passed_time":5.533006062,"remaining_time":0.9917652376},
{"learn":[0.02637343949],"iteration":848,"passed_time":5.539072008,"remaining_time":0.9851588612},
{"learn":[0.02633083019],"iteration":849,"passed_time":5.545650181,"remaining_time":0.9786441496},
{"learn":[0.02629733363],"iteration":850,"passed_time":5.552073197,"remaining_time":0.9721021226},
{"learn":[0.02626769755],"iteration":851,"passed_time":5.558280662,"remaining_time":0.9655229319},
{"learn":[0.02624990798],"iteration":852,"passed_time":5.564470399,"remaining_time":0.9589415577},
{"learn":[0.02622305138],"iteration":853,"passed_time":5.571054145,"remaining_time":0.9524284603},
{"learn":[0.02619368419],"iteration":854,"passed_time":5.577794306,"remaining_time":0.9459417244},
{"learn":[0.02616251669],"iteration":855,"passed_time":5.584493452,"remaining_time":0.9394474967},
{"learn":[0.02615388216],"iteration":856,"passed_time":5.59077497,"remaining_time":0.9328831047},
{"learn":[0.02612809019],"iteration":857,"passed_time":5.59904816,"remaining_time":0.9266489962},
{"learn":[0.0261054559],"iteration":858,"passed_time":5.607104199,"remaining_time":0.9203744959},
{"learn":[0.02608566808],"iteration":859,"passed_time":5.614622202,"remaining_time":0.9140082654},
{"learn":[0.02606066746],"iteration":860,"passed_time":5.62149698,"remaining_time":0.907535517},
{"learn":[0.02601190784],"iteration":861,"passed_time":5.628682644,"remaining_time":0.9011116065},
{"learn":[0.02596893859],"iteration":862,"passed_time":5.635748812,"remaining_time":0.8946669609},
{"learn":[0.02594419317],"iteration":863,"passed_time":5.642554871,"remaining_time":0.8881799334},
{"learn":[0.02590890188],"iteration":864,"passed_time":5.64905218,"remaining_time":0.8816439818},
{"learn":[0.02587359512],"iteration":865,"passed_time":5.655754132,"remaining_time":0.8751397848},
{"learn":[0.02580807165],"iteration":866,"passed_time":5.664359607,"remaining_time":0.868927137},
{"learn":[0.02577907695],"iteration":867,"passed_time":5.671919333,"remaining_time":0.8625499446},
{"learn":[0.02573723125],"iteration":868,"passed_time":5.678965322,"remaining_time":0.8560925859},
{"learn":[0.02569705544],"iteration":869,"passed_time":5.686196224,"remaining_time":0.8496615048},
{"learn":[0.02566264966],"iteration":870,"passed_time":5.694284256,"remaining_time":0.8433555328},
{"learn":[0.02560973475],"iteration":871,"passed_time":5.701591068,"remaining_time":0.836930799},
{"learn":[0.0255727696],"iteration":872,"passed_time":5.709415742,"remaining_time":0.8305793806},
{"learn":[0.02552761048],"iteration":873,"passed_time":5.716618776,"remaining_time":0.8241349723},
{"learn":[0.02545536462],"iteration":874,"passed_time":5.723361828,"remaining_time":0.8176231183},
{"learn":[0.02540195128],"iteration":875,"passed_time":5.729921097,"remaining_time":0.8110847215},
{"learn":[0.02536255638],"iteration":876,"passed_time":5.736588759,"remaining_time":0.8045614794},
{"learn":[0.02534044013],"iteration":877,"passed_time":5.743017604,"remaining_time":0.798004724},
{"learn":[0.02529968129],"iteration":878,"passed_time":5.749265662,"remaining_time":0.7914233732},
{"learn":[0.02523718513],"iteration":879,"passed_time":5.75542404,"remaining_time":0.7848305509},
{"learn":[0.02518685296],"iteration":880,"passed_time":5.761646757,"remaining_time":0.7782474053},
{"learn":[0.02513875129],"iteration":881,"passed_time":5.768179524,"remaining_time":0.7717065576},
{"learn":[0.02511458803],"iteration":882,"passed_time":5.774361107,"remaining_time":0.7651191953},
{"learn":[0.02505563706],"iteration":883,"passed_time":5.780938083,"remaining_time":0.7585846354},
{"learn":[0.02500704926],"iteration":884,"passed_time":5.78761101,"remaining_time":0.7520624476},
{"learn":[0.02496994142],"iteration":885,"passed_time":5.793891994,"remaining_time":0.745489489},
{"learn":[0.02494694684],"iteration":886,"passed_time":5.800371984,"remaining_time":0.7389425413},
{"learn":[0.02493679338],"iteration":887,"passed_time":5.806489455,"remaining_time":0.7323500214},
{"learn":[0.02491381639],"iteration":888,"passed_time":5.812919915,"remaining_time":0.7257976496},
{"learn":[0.02489992677],"iteration":889,"passed_time":5.819052243,"remaining_time":0.7192087042},
{"learn":[0.02487247057],"iteration":890,"passed_time":5.82521076,"remaining_time":0.7126239875},
{"learn":[0.02483439808],"iteration":891,"passed_time":5.831778049,"remaining_time":0.7060897189},
{"learn":[0.02479056955],"iteration":892,"passed_time":5.83821846,"remaining_time":0.6995401739},
{"learn":[0.02474215503],"iteration":893,"passed_time":5.844715274,"remaining_time":0.6929975604},
{"learn":[0.0246961814],"iteration":894,"passed_time":5.85133537,"remaining_time":0.6864695126},
{"learn":[0.02466101354],"iteration":895,"passed_time":5.858025255,"remaining_time":0.6799493599},
{"learn":[0.02463865776],"iteration":896,"passed_time":5.864192546,"remaining_time":0.6733688207},
{"learn":[0.02461420282],"iteration":897,"passed_time":5.870415779,"remaining_time":0.6667955562},
{"learn":[0.0245951249],"iteration":898,"passed_time":5.876887368,"remaining_time":0.6602509724},
{"learn":[0.02457310963],"iteration":899,"passed_time":5.883266673,"remaining_time":0.653696297},
{"learn":[0.02451528],"iteration":900,"passed_time":5.88964509,"remaining_time":0.6471419134},
{"learn":[0.0244939036],"iteration":901,"passed_time":5.895961045,"remaining_time":0.6405811335},
{"learn":[0.02447472616],"iteration":902,"passed_time":5.902285182,"remaining_time":0.6340217748},
{"learn":[0.02444143738],"iteration":903,"passed_time":5.909089912,"remaining_time":0.627513973},
{"learn":[0.02441026412],"iteration":904,"passed_time":5.915712925,"remaining_time":0.6209864396},
{"learn":[0.02438803484],"iteration":905,"passed_time":5.922570495,"remaining_time":0.6144830315},
{"learn":[0.02434311888],"iteration":906,"passed_time":5.929423204,"remaining_time":0.6079783439},
{"learn":[0.02429821642],"iteration":907,"passed_time":5.935960016,"remaining_time":0.6014408827},
{"learn":[0.02425778462],"iteration":908,"passed_time":5.94250634,"remaining_time":0.5949043751},
{"learn":[0.02423664561],"iteration":909,"passed_time":5.948808427,"remaining_time":0.5883436906},
{"learn":[0.02421650494],"iteration":910,"passed_time":5.95533903,"remaining_time":0.5818058986},
{"learn":[0.02418663984],"iteration":911,"passed_time":5.962028494,"remaining_time":0.5752834512},
{"learn":[0.02417526421],"iteration":912,"passed_time":5.968741131,"remaining_time":0.568762846},
{"learn":[0.02414959866],"iteration":913,"passed_time":5.975403663,"remaining_time":0.5622371062},
{"learn":[0.02411559233],"iteration":914,"passed_time":5.98183886,"remaining_time":0.5556899487},
{"learn":[0.02408827896],"iteration":915,"passed_time":5.988083792,"remaining_time":0.5491255879},
{"learn":[0.02404977284],"iteration":916,"passed_time":5.994286119,"remaining_time":0.5425580675},
{"learn":[0.02402135743],"iteration":917,"passed_time":6.00050789,"remaining_time":0.5359930795},
{"learn":[0.02398817359],"iteration":918,"passed_time":6.006847371,"remaining_time":0.5294392133},
{"learn":[0.02394800381],"iteration":919,"passed_time":6.013376464,"remaining_time":0.5229023012},
{"learn":[0.02393479808],"iteration":920,"passed_time":6.019705925,"remaining_time":0.5163482824},
{"learn":[0.02390177795],"iteration":921,"passed_time":6.026131402,"remaining_time":0.5098028735},
{"learn":[0.02389425092],"iteration":922,"passed_time":6.032123569,"remaining_time":0.5032215762},
{"learn":[0.02385682422],"iteration":923,"passed_time":6.038522061,"remaining_time":0.4966749747},
{"learn":[0.02381659094],"iteration":924,"passed_time":6.045065704,"remaining_time":0.4901404625},
{"learn":[0.02378269092],"iteration":925,"passed_time":6.051388305,"remaining_time":0.4835882663},
{"learn":[0.02376267294],"iteration":926,"passed_time":6.057776308,"remaining_time":0.4770417157},
{"learn":[0.02372091181],"iteration":927,"passed_time":6.064652308,"remaining_time":0.4705333687},
{"learn":[0.02368333915],"iteration":928,"passed_time":6.071544258,"remaining_time":0.4640254492},
{"learn":[0.02362737139],"iteration":929,"passed_time":6.07855252,"remaining_time":0.4575254585},
{"learn":[0.02359841619],"iteration":930,"passed_time":6.085098559,"remaining_time":0.4509901187},
{"learn":[0.0235587265],"iteration":931,"passed_time":6.091469134,"remaining_time":0.444441954},
{"learn":[0.0235088196],"iteration":932,"passed_time":6.098171703,"remaining_time":0.4379180108},
{"learn":[0.02348747433],"iteration":933,"passed_time":6.104714691,"remaining_time":0.4313824085},
{"learn":[0.02347427357],"iteration":934,"passed_time":6.111430053,"remaining_time":0.4248587738},
{"learn":[0.02344283167],"iteration":935,"passed_time":6.118139019,"remaining_time":0.4183342919},
{"learn":[0.02343144749],"iteration":936,"passed_time":6.124718151,"remaining_time":0.4118006868},
{"learn":[0.02340099635],"iteration":937,"passed_time":6.131503545,"remaining_time":0.4052806181},
{"learn":[0.02335366334],"iteration":938,"passed_time":6.138004242,"remaining_time":0.3987414896},
{"learn":[0.02333344538],"iteration":939,"passed_time":6.144491652,"remaining_time":0.3922015948},
{"learn":[0.02332075273],"iteration":940,"passed_time":6.150692646,"remaining_time":0.3856438535},
{"learn":[0.02328638437],"iteration":941,"passed_time":6.157032142,"remaining_time":0.3790953973},
{"learn":[0.02326729367],"iteration":942,"passed_time":6.163683879,"remaining_time":0.3725662578},
{"learn":[0.02323465268],"iteration":943,"passed_time":6.170431168,"remaining_time":0.3660425269},
{"learn":[0.02320399182],"iteration":944,"passed_time":6.176947536,"remaining_time":0.3595048831},
{"learn":[0.02315641612],"iteration":945,"passed_time":6.1834949,"remaining_time":0.3529690535},
{"learn":[0.02312026219],"iteration":946,"passed_time":6.190367678,"remaining_time":0.3464514118},
{"learn":[0.0230839422],"iteration":947,"passed_time":6.197366375,"remaining_time":0.3399399277},
{"learn":[0.0230707197],"iteration":948,"passed_time":6.204855598,"remaining_time":0.3334537782},
{"learn":[0.02302760188],"iteration":949,"passed_time":6.21401352,"remaining_time":0.3270533431},
{"learn":[0.02300382206],"iteration":950,"passed_time":6.223211186,"remaining_time":0.3206491568},
{"learn":[0.02298839103],"iteration":951,"passed_time":6.231707189,"remaining_time":0.3142037238},
{"learn":[0.02296619343],"iteration":952,"passed_time":6.258123427,"remaining_time":0.3086377766},
{"learn":[0.02294043025],"iteration":953,"passed_time":6.268904974,"remaining_time":0.3022742441},
{"learn":[0.02290515398],"iteration":954,"passed_time":6.279591608,"remaining_time":0.2958969868},
{"learn":[0.02287479709],"iteration":955,"passed_time":6.289373368,"remaining_time":0.2894690671},
{"learn":[0.02284205618],"iteration":956,"passed_time":6.299638869,"remaining_time":0.283055874},
{"learn":[0.02282199742],"iteration":957,"passed_time":6.310599538,"remaining_time":0.2766651155},
{"learn":[0.02280268451],"iteration":958,"passed_time":6.321741868,"remaining_time":0.2702725929},
{"learn":[0.02277448858],"iteration":959,"passed_time":6.332083742,"remaining_time":0.2638368226},
{"learn":[0.02274519108],"iteration":960,"passed_time":6.342763339,"remaining_time":0.2574066288},
{"learn":[0.02271108917],"iteration":961,"passed_time":6.353593002,"remaining_time":0.2509735281},
{"learn":[0.02268724108],"iteration":962,"passed_time":6.36519066,"remaining_time":0.2445608042},
{"learn":[0.02267829267],"iteration":963,"passed_time":6.375836341,"remaining_time":0.2381017721},
{"learn":[0.02264498473],"iteration":964,"passed_time":6.388531602,"remaining_time":0.2317084001},
{"learn":[0.02262708283],"iteration":965,"passed_time":6.400819667,"remaining_time":0.2252876487},
{"learn":[0.02259989014],"iteration":966,"passed_time":6.41683514,"remaining_time":0.2189819644},
{"learn":[0.02258298945],"iteration":967,"passed_time":6.428777753,"remaining_time":0.2125215786},
{"learn":[0.02253399351],"iteration":968,"passed_time":6.439794557,"remaining_time":0.2060202593},
{"learn":[0.0224847972],"iteration":969,"passed_time":6.452670985,"remaining_time":0.1995671439},
{"learn":[0.02243115026],"iteration":970,"passed_time":6.464903085,"remaining_time":0.1930815545},
{"learn":[0.02239205887],"iteration":971,"passed_time":6.476336442,"remaining_time":0.1865611321},
{"learn":[0.02236253552],"iteration":972,"passed_time":6.487826426,"remaining_time":0.1800321824},
{"learn":[0.02235372888],"iteration":973,"passed_time":6.498710155,"remaining_time":0.1734768625},
{"learn":[0.02233158553],"iteration":974,"passed_time":6.510131912,"remaining_time":0.1669264593},
{"learn":[0.02231962332],"iteration":975,"passed_time":6.521453585,"remaining_time":0.1603636128},
{"learn":[0.02228561748],"iteration":976,"passed_time":6.533934165,"remaining_time":0.1538183069},
{"learn":[0.02225233672],"iteration":977,"passed_time":6.545148056,"remaining_time":0.1472323694},
{"learn":[0.02221324992],"iteration":978,"passed_time":6.560273296,"remaining_time":0.1407208776},
{"learn":[0.02218185031],"iteration":979,"passed_time":6.573058364,"remaining_time":0.1341440482},
{"learn":[0.02215942973],"iteration":980,"passed_time":6.584014229,"remaining_time":0.1275191339},
{"learn":[0.02213394025],"iteration":981,"passed_time":6.595056755,"remaining_time":0.1208869874},
{"learn":[0.02212406704],"iteration":982,"passed_time":6.60535436,"remaining_time":0.1142329849},
{"learn":[0.02210793922],"iteration":983,"passed_time":6.61663151,"remaining_time":0.1075875042},
{"learn":[0.02209515788],"iteration":984,"passed_time":6.627889047,"remaining_time":0.1009323205},
{"learn":[0.02206756098],"iteration":985,"passed_time":6.638513102,"remaining_time":0.09425880672},
{"learn":[0.02202383679],"iteration":986,"passed_time":6.650033531,"remaining_time":0.08758909413},
{"learn":[0.02200161467],"iteration":987,"passed_time":6.660723584,"remaining_time":0.08089947673},
{"learn":[0.02197699683],"iteration":988,"passed_time":6.671237158,"remaining_time":0.07419980661},
{"learn":[0.02195754697],"iteration":989,"passed_time":6.695052539,"remaining_time":0.06762679332},
{"learn":[0.02190808973],"iteration":990,"passed_time":6.707390084,"remaining_time":0.06091474345},
{"learn":[0.02187095597],"iteration":991,"passed_time":6.719316644,"remaining_time":0.05418803745},
{"learn":[0.02185434376],"iteration":992,"passed_time":6.731200133,"remaining_time":0.04745055481},
{"learn":[0.02184764694],"iteration":993,"passed_time":6.742810672,"remaining_time":0.04070107045},
{"learn":[0.02183547381],"iteration":994,"passed_time":6.753482887,"remaining_time":0.03393709994},
{"learn":[0.02180598365],"iteration":995,"passed_time":6.76614557,"remaining_time":0.02717327538},
{"learn":[0.02178550032],"iteration":996,"passed_time":6.777230665,"remaining_time":0.02039287061},
{"learn":[0.0217661545],"iteration":997,"passed_time":6.787327795,"remaining_time":0.01360185931},
{"learn":[0.02171936126],"iteration":998,"passed_time":6.796888577,"remaining_time":0.00680369227},
{"learn":[0.02171115581],"iteration":999,"passed_time":6.806186747,"remaining_time":0}
]}